{"customerId":"0ac98a3b-571f-11ee-e541-70352bbf788c","sales":[{"id":"15c5ec69-8ad8-9313-11f0-eccbffbe71c0","outlet_id":"06819b3a-2e91-11ed-f9a0-c4d550292f42","register_id":"06819b3a-2e91-11ed-f9a0-c4d5502c87f5","user_id":"7ff35c1e-54a6-4441-ab36-a5775a7d7d81","customer_id":"0ac98a3b-571f-11ee-e541-70352bbf788c","invoice_number":"76453","source":"USER","source_id":null,"complete_open_sequence_id":null,"accounts_transaction_id":null,"has_unsynced_on_account_payments":null,"status":"CLOSED","state":"closed","note":"","short_code":"93o8jx","return_for":null,"return_ids":[],"total_loyalty":0.1528,"created_at":"2026-01-08T19:57:03+00:00","updated_at":"2026-01-08T19:57:03+00:00","sale_date":"2026-01-08T19:57:03+00:00","deleted_at":null,"line_items":[{"id":"15c5ec69-8ad8-9313-11f0-eccc1c4b1848","product_id":"4695678e-49a4-4bf7-a9a3-202db8c08139","salesperson_id":null,"tax_id":"0ac98a3b-571f-11ee-e863-17c0bf50ac3a","discount_total":0,"discount":0,"price_total":6,"price":6,"cost_total":3,"cost":3,"tax_total":0.945,"tax":0.945,"quantity":1,"loyalty_value":0.18,"note":null,"return_reason":null,"price_set":false,"status":"CONFIRMED","sequence":2,"gift_card_number":null,"tax_components":[{"rate_id":"b532b2b4-dec4-11ed-8863-0ac98a3b57fb","total_tax":0.42},{"rate_id":"b532df5a-dec4-11ed-8863-0ac98a3b57fb","total_tax":0.165},{"rate_id":"79a5e97e-17c0-11ee-8863-0ac98a3b57fb","total_tax":0.36}],"promotions":[],"surcharges":[],"total_tax":0.945,"total_price":6,"unit_discount":0,"unit_price":6,"unit_tax":0.945,"unit_loyalty_value":0.18,"total_cost":3,"total_discount":0,"total_loyalty_value":0.18,"unit_cost":3,"is_return":false}],"payments":[{"id":"15c5ec69-8ad8-9313-11f0-eccc27bbcf1a","register_id":"06819b3a-2e91-11ed-f9a0-c4d5502c87f5","register_open_sequence_id":"02269032-111f-11f0-fa97-eca12f50fe99","outlet_id":"06819b3a-2e91-11ed-f9a0-c4d550292f42","retailer_payment_type_id":"caa7892a-6159-4441-80e8-6a27ea6c8960","payment_type_id":"106","name":"Loyalty","amount":1.05,"payment_date":"2026-01-08T19:56:43+00:00","deleted_at":null,"external_attributes":[],"external_applications":[],"surcharge":null,"source_id":null},{"id":"15c5ec69-8ad8-9313-11f0-eccc32934904","register_id":"06819b3a-2e91-11ed-f9a0-c4d5502c87f5","register_open_sequence_id":"02269032-111f-11f0-fa97-eca12f50fe99","outlet_id":"06819b3a-2e91-11ed-f9a0-c4d550292f42","retailer_payment_type_id":"a5237779-ff58-4cdc-bdb9-45cc65d6db45","payment_type_id":"1","name":"Cash","amount":6,"payment_date":"2026-01-08T19:57:01+00:00","deleted_at":null,"external_attributes":[],"external_applications":[],"surcharge":null,"source_id":null},{"id":"15c5ec69-8ad8-9313-11f0-eccc338366be","register_id":"06819b3a-2e91-11ed-f9a0-c4d5502c87f5","register_open_sequence_id":"02269032-111f-11f0-fa97-eca12f50fe99","outlet_id":"06819b3a-2e91-11ed-f9a0-c4d550292f42","retailer_payment_type_id":"a5237779-ff58-4cdc-bdb9-45cc65d6db45","payment_type_id":"1","name":"Cash","amount":-0.1,"payment_date":"2026-01-08T19:57:03+00:00","deleted_at":null,"external_attributes":[],"external_applications":[],"surcharge":null,"source_id":null}],"adjustments":[],"external_applications":[],"attributes":[],"version":48642387428,"ecom_custom_charges":{"charges":[],"total":0,"total_tax":0,"total_incl":0},"total_tax":0.95,"receipt_number":"76453","total_price":6,"total_price_incl":6.945,"total_surcharge":0,"taxes":[{"amount":0.42,"id":"b532b2b4-dec4-11ed-8863-0ac98a3b57fb"},{"amount":0.165,"id":"b532df5a-dec4-11ed-8863-0ac98a3b57fb"},{"amount":0.36,"id":"79a5e97e-17c0-11ee-8863-0ac98a3b57fb"}],"_isEcomOrder":""},{"id":"b3469629-e07e-91c2-11ee-f68b689a178c","outlet_id":"06819b3a-2e91-11ed-f9a0-c4d550292f42","register_id":"06819b3a-2e91-11ed-f9a0-c4d5502c87f5","user_id":"db868521-a422-42d8-9486-c55b5f88da4f","customer_id":"0ac98a3b-571f-11ee-e541-70352bbf788c","invoice_number":"17713","source":"USER","source_id":null,"complete_open_sequence_id":null,"accounts_transaction_id":null,"has_unsynced_on_account_payments":null,"status":"CLOSED","state":"closed","note":"Tuesday special","short_code":"cs9fe6","return_for":null,"return_ids":[],"total_loyalty":1.05,"created_at":"2024-04-09T16:09:07+00:00","updated_at":"2024-04-09T16:09:07+00:00","sale_date":"2024-04-09T16:09:07+00:00","deleted_at":null,"line_items":[{"id":"b3469629-e07e-91c2-11ee-f68b68a522bc","product_id":"06819b3a-2e1f-11ed-f9a0-c4d5522bf959","salesperson_id":null,"tax_id":"06819b3a-2e91-11ed-f9a0-c4d5502316f5","discount_total":0,"discount":0,"price_total":-5.25,"price":5.25,"cost_total":0,"cost":0,"tax_total":-0.82688,"tax":0.82688,"quantity":-1,"loyalty_value":0,"note":null,"return_reason":null,"price_set":false,"status":"CONFIRMED","sequence":3,"gift_card_number":null,"tax_components":[{"rate_id":"b532b2b4-dec4-11ed-8863-0ac98a3b57fb","total_tax":-0.3675},{"rate_id":"b532df5a-dec4-11ed-8863-0ac98a3b57fb","total_tax":-0.14438},{"rate_id":"79a5e97e-17c0-11ee-8863-0ac98a3b57fb","total_tax":-0.315}],"promotions":[],"surcharges":[],"total_tax":-0.82688,"total_price":-5.25,"unit_discount":0,"unit_price":5.25,"unit_tax":0.82688,"unit_loyalty_value":0,"total_cost":0,"total_discount":0,"total_loyalty_value":0,"unit_cost":0,"is_return":false},{"id":"b3469629-e07e-91c2-11ee-f68b6fc3a7e4","product_id":"bdc9415c-6ae7-43fb-a506-a85d43bbe9b2","salesperson_id":null,"tax_id":"0ac98a3b-571f-11ee-e863-17c0bf50ac3a","discount_total":0,"discount":0,"price_total":35,"price":35,"cost_total":18.06818,"cost":18.06818,"tax_total":5.5125,"tax":5.5125,"quantity":1,"loyalty_value":1.05,"note":null,"return_reason":null,"price_set":false,"status":"CONFIRMED","sequence":2,"gift_card_number":null,"tax_components":[{"rate_id":"b532b2b4-dec4-11ed-8863-0ac98a3b57fb","total_tax":2.45},{"rate_id":"b532df5a-dec4-11ed-8863-0ac98a3b57fb","total_tax":0.9625},{"rate_id":"79a5e97e-17c0-11ee-8863-0ac98a3b57fb","total_tax":2.1}],"promotions":[],"surcharges":[],"total_tax":5.5125,"total_price":35,"unit_discount":0,"unit_price":35,"unit_tax":5.5125,"unit_loyalty_value":1.05,"total_cost":18.06818,"total_discount":0,"total_loyalty_value":1.05,"unit_cost":18.06818,"is_return":false}],"payments":[{"id":"b3469629-e07e-91c2-11ee-f68b7c7c6cd2","register_id":"06819b3a-2e91-11ed-f9a0-c4d5502c87f5","register_open_sequence_id":"06deecd2-a11f-11ee-e6bb-f67f0dac54ec","outlet_id":"06819b3a-2e91-11ed-f9a0-c4d550292f42","retailer_payment_type_id":"a5237779-ff58-4cdc-bdb9-45cc65d6db45","payment_type_id":"1","name":"Cash","amount":100,"payment_date":"2024-04-09T16:09:04+00:00","deleted_at":null,"external_attributes":[],"external_applications":[],"surcharge":null,"source_id":null},{"id":"b3469629-e07e-91c2-11ee-f68b7e1e456a","register_id":"06819b3a-2e91-11ed-f9a0-c4d5502c87f5","register_open_sequence_id":"06deecd2-a11f-11ee-e6bb-f67f0dac54ec","outlet_id":"06819b3a-2e91-11ed-f9a0-c4d550292f42","retailer_payment_type_id":"a5237779-ff58-4cdc-bdb9-45cc65d6db45","payment_type_id":"1","name":"Cash","amount":-65.56,"payment_date":"2024-04-09T16:09:07+00:00","deleted_at":null,"external_attributes":[],"external_applications":[],"surcharge":null,"source_id":null}],"adjustments":[],"external_applications":[],"attributes":[],"version":35335960986,"ecom_custom_charges":{"charges":[],"total":0,"total_tax":0,"total_incl":0},"total_tax":4.69,"receipt_number":"17713","total_price":29.75,"total_price_incl":34.43562,"total_surcharge":0,"taxes":[{"amount":2.0825,"id":"b532b2b4-dec4-11ed-8863-0ac98a3b57fb"},{"amount":0.81812,"id":"b532df5a-dec4-11ed-8863-0ac98a3b57fb"},{"amount":1.785,"id":"79a5e97e-17c0-11ee-8863-0ac98a3b57fb"}],"_isEcomOrder":false},{"id":"ffeefa23-8c2b-a218-11ee-70335934a354","outlet_id":"06819b3a-2e91-11ed-f9a0-c4d550292f42","register_id":"06819b3a-2e91-11ed-f9a0-c4d5502c87f5","user_id":"1170479a-d0c4-456d-a91b-89f09b25ff70","customer_id":"0ac98a3b-571f-11ee-e541-70352bbf788c","invoice_number":"6068","source":"USER","source_id":null,"complete_open_sequence_id":null,"accounts_transaction_id":null,"has_unsynced_on_account_payments":null,"status":"CLOSED","state":"closed","note":"","short_code":"5zexnw","return_for":null,"return_ids":[],"total_loyalty":0,"created_at":"2023-10-21T17:14:04+00:00","updated_at":"2023-10-21T17:14:04+00:00","sale_date":"2023-10-21T17:13:53+00:00","deleted_at":null,"line_items":[{"id":"ffeefa23-8c2b-a218-11ee-70350b7878dc","product_id":"7b712ae4-6a47-4977-9771-b74efa35fe45","salesperson_id":null,"tax_id":"0ac98a3b-571f-11ee-e863-17c0bf50ac3a","discount_total":5,"discount":5,"price_total":15,"price":15,"cost_total":9,"cost":9,"tax_total":2.3625,"tax":2.3625,"quantity":1,"loyalty_value":0,"note":null,"return_reason":null,"price_set":false,"status":"CONFIRMED","sequence":2,"gift_card_number":null,"tax_components":[{"rate_id":"b532b2b4-dec4-11ed-8863-0ac98a3b57fb","total_tax":1.05},{"rate_id":"b532df5a-dec4-11ed-8863-0ac98a3b57fb","total_tax":0.4125},{"rate_id":"79a5e97e-17c0-11ee-8863-0ac98a3b57fb","total_tax":0.9}],"promotions":[{"amount":-5,"name":"25%  OFF Bad Days/TreHouse","promotion_id":"1705711316927623168","promo_code":"","promo_code_id":"0"}],"surcharges":[],"total_tax":2.3625,"total_price":15,"unit_discount":5,"unit_price":15,"unit_tax":2.3625,"unit_loyalty_value":0,"total_cost":9,"total_discount":5,"total_loyalty_value":0,"unit_cost":9,"is_return":false},{"id":"ffeefa23-8c2b-a218-11ee-70350c109978","product_id":"f1f9f1ce-a489-4f7d-9c60-03fe10e5ab9c","salesperson_id":null,"tax_id":"0ac98a3b-571f-11ee-e863-17c0bf50ac3a","discount_total":5,"discount":5,"price_total":15,"price":15,"cost_total":9,"cost":9,"tax_total":2.3625,"tax":2.3625,"quantity":1,"loyalty_value":0,"note":null,"return_reason":null,"price_set":false,"status":"CONFIRMED","sequence":3,"gift_card_number":null,"tax_components":[{"rate_id":"b532b2b4-dec4-11ed-8863-0ac98a3b57fb","total_tax":1.05},{"rate_id":"b532df5a-dec4-11ed-8863-0ac98a3b57fb","total_tax":0.4125},{"rate_id":"79a5e97e-17c0-11ee-8863-0ac98a3b57fb","total_tax":0.9}],"promotions":[{"amount":-5,"name":"25%  OFF Bad Days/TreHouse","promotion_id":"1705711316927623168","promo_code":"","promo_code_id":"0"}],"surcharges":[],"total_tax":2.3625,"total_price":15,"unit_discount":5,"unit_price":15,"unit_tax":2.3625,"unit_loyalty_value":0,"total_cost":9,"total_discount":5,"total_loyalty_value":0,"unit_cost":9,"is_return":false}],"payments":[{"id":"ffeefa23-8c2b-a218-11ee-703533feb550","register_id":"06819b3a-2e91-11ed-f9a0-c4d5502c87f5","register_open_sequence_id":"0ac98a3b-571f-11ee-e541-70224bbd49b3","outlet_id":"06819b3a-2e91-11ed-f9a0-c4d550292f42","retailer_payment_type_id":"a5237779-ff58-4cdc-bdb9-45cc65d6db45","payment_type_id":"1","name":"Cash","amount":100,"payment_date":"2023-10-21T17:13:50+00:00","deleted_at":null,"external_attributes":[],"external_applications":[],"surcharge":null,"source_id":null},{"id":"ffeefa23-8c2b-a218-11ee-703535b51470","register_id":"06819b3a-2e91-11ed-f9a0-c4d5502c87f5","register_open_sequence_id":"0ac98a3b-571f-11ee-e541-70224bbd49b3","outlet_id":"06819b3a-2e91-11ed-f9a0-c4d550292f42","retailer_payment_type_id":"a5237779-ff58-4cdc-bdb9-45cc65d6db45","payment_type_id":"1","name":"Cash","amount":-65.27,"payment_date":"2023-10-21T17:13:53+00:00","deleted_at":null,"external_attributes":[],"external_applications":[],"surcharge":null,"source_id":null}],"adjustments":[],"external_applications":[],"attributes":[],"version":32167303243,"ecom_custom_charges":{"charges":[],"total":0,"total_tax":0,"total_incl":0},"total_tax":4.73,"receipt_number":"6068","total_price":30,"total_price_incl":34.725,"total_surcharge":0,"taxes":[{"amount":2.1,"id":"b532b2b4-dec4-11ed-8863-0ac98a3b57fb"},{"amount":0.825,"id":"b532df5a-dec4-11ed-8863-0ac98a3b57fb"},{"amount":1.8,"id":"79a5e97e-17c0-11ee-8863-0ac98a3b57fb"}],"_isEcomOrder":""}],"cachedAt":"2026-01-15T17:21:24.123Z"}