{"customerId":"0282e8ff-bc1f-11ef-f633-b8bbb494076d","sales":[{"id":"2f1f7857-757d-a4ba-11f0-ced26d1150fc","outlet_id":"06819b3a-2e91-11ed-f9a0-c4d550292f42","register_id":"06819b3a-2e91-11ed-f9a0-c4d5502c87f5","user_id":"71bd9f52-ced2-4397-b7ff-afaa511b8fc5","customer_id":"0282e8ff-bc1f-11ef-f633-b8bbb494076d","invoice_number":"72419","source":"USER","source_id":null,"complete_open_sequence_id":null,"accounts_transaction_id":null,"has_unsynced_on_account_payments":null,"status":"CLOSED","state":"closed","note":"","short_code":"m84z5v","return_for":null,"return_ids":[],"total_loyalty":0,"created_at":"2025-12-01T16:30:06+00:00","updated_at":"2025-12-01T16:30:06+00:00","sale_date":"2025-12-01T16:30:05+00:00","deleted_at":null,"line_items":[{"id":"2f1f7857-757d-a4ba-11f0-ced2b0e7cb44","product_id":"ab54dc0b-0219-44e0-b839-bde03a5c2c16","salesperson_id":null,"tax_id":"0ac98a3b-571f-11ee-e863-17c0bf50ac3a","discount_total":4.2,"discount":4.2,"price_total":23.8,"price":23.8,"cost_total":14,"cost":14,"tax_total":3.7485,"tax":3.7485,"quantity":1,"loyalty_value":0,"note":null,"return_reason":null,"price_set":false,"status":"CONFIRMED","sequence":2,"gift_card_number":null,"tax_components":[{"rate_id":"b532b2b4-dec4-11ed-8863-0ac98a3b57fb","total_tax":1.666},{"rate_id":"b532df5a-dec4-11ed-8863-0ac98a3b57fb","total_tax":0.6545},{"rate_id":"79a5e97e-17c0-11ee-8863-0ac98a3b57fb","total_tax":1.428}],"promotions":[{"amount":-4.2,"name":"Munchie Monday - 15% off","promotion_id":"1660675781346959360","promo_code":"","promo_code_id":"0"}],"surcharges":[],"total_tax":3.7485,"total_price":23.8,"unit_discount":4.2,"unit_price":23.8,"unit_tax":3.7485,"unit_loyalty_value":0,"total_cost":14,"total_discount":4.2,"total_loyalty_value":0,"unit_cost":14,"is_return":false},{"id":"2f1f7857-757d-a4ba-11f0-ced2b1fda620","product_id":"d0b67012-9894-42de-8651-8c1044b01859","salesperson_id":null,"tax_id":"0ac98a3b-571f-11ee-e863-17c0bf50ac3a","discount_total":6,"discount":6,"price_total":34,"price":34,"cost_total":16.04225,"cost":16.04225,"tax_total":5.355,"tax":5.355,"quantity":1,"loyalty_value":0,"note":null,"return_reason":null,"price_set":false,"status":"CONFIRMED","sequence":3,"gift_card_number":null,"tax_components":[{"rate_id":"b532b2b4-dec4-11ed-8863-0ac98a3b57fb","total_tax":2.38},{"rate_id":"b532df5a-dec4-11ed-8863-0ac98a3b57fb","total_tax":0.935},{"rate_id":"79a5e97e-17c0-11ee-8863-0ac98a3b57fb","total_tax":2.04}],"promotions":[{"amount":-6,"name":"Munchie Monday - 15% off","promotion_id":"1660675781346959360","promo_code":"","promo_code_id":"0"}],"surcharges":[],"total_tax":5.355,"total_price":34,"unit_discount":6,"unit_price":34,"unit_tax":5.355,"unit_loyalty_value":0,"total_cost":16.04225,"total_discount":6,"total_loyalty_value":0,"unit_cost":16.04225,"is_return":false},{"id":"2f1f7857-757d-a4ba-11f0-ced2cfe49784","product_id":"63d6d6ce-f563-4518-86a9-cc32c6896378","salesperson_id":null,"tax_id":"0ac98a3b-571f-11ee-e863-17c0bf50ac3a","discount_total":6,"discount":6,"price_total":34,"price":34,"cost_total":16,"cost":16,"tax_total":5.355,"tax":5.355,"quantity":1,"loyalty_value":0,"note":null,"return_reason":null,"price_set":false,"status":"CONFIRMED","sequence":4,"gift_card_number":null,"tax_components":[{"rate_id":"b532b2b4-dec4-11ed-8863-0ac98a3b57fb","total_tax":2.38},{"rate_id":"b532df5a-dec4-11ed-8863-0ac98a3b57fb","total_tax":0.935},{"rate_id":"79a5e97e-17c0-11ee-8863-0ac98a3b57fb","total_tax":2.04}],"promotions":[{"amount":-6,"name":"Munchie Monday - 15% off","promotion_id":"1660675781346959360","promo_code":"","promo_code_id":"0"}],"surcharges":[],"total_tax":5.355,"total_price":34,"unit_discount":6,"unit_price":34,"unit_tax":5.355,"unit_loyalty_value":0,"total_cost":16,"total_discount":6,"total_loyalty_value":0,"unit_cost":16,"is_return":false}],"payments":[{"id":"2f1f7857-757d-a4ba-11f0-ced2fc46d76a","register_id":"06819b3a-2e91-11ed-f9a0-c4d5502c87f5","register_open_sequence_id":"02269032-111f-11f0-fa97-cec53cc49f49","outlet_id":"06819b3a-2e91-11ed-f9a0-c4d550292f42","retailer_payment_type_id":"a5237779-ff58-4cdc-bdb9-45cc65d6db45","payment_type_id":"1","name":"Cash","amount":120,"payment_date":"2025-12-01T16:30:01+00:00","deleted_at":null,"external_attributes":[],"external_applications":[],"surcharge":null,"source_id":null},{"id":"2f1f7857-757d-a4ba-11f0-ced2fea27640","register_id":"06819b3a-2e91-11ed-f9a0-c4d5502c87f5","register_open_sequence_id":"02269032-111f-11f0-fa97-cec53cc49f49","outlet_id":"06819b3a-2e91-11ed-f9a0-c4d550292f42","retailer_payment_type_id":"a5237779-ff58-4cdc-bdb9-45cc65d6db45","payment_type_id":"1","name":"Cash","amount":-13.74,"payment_date":"2025-12-01T16:30:05+00:00","deleted_at":null,"external_attributes":[],"external_applications":[],"surcharge":null,"source_id":null}],"adjustments":[],"external_applications":[],"attributes":[],"version":47713092941,"ecom_custom_charges":{"charges":[],"total":0,"total_tax":0,"total_incl":0},"total_tax":14.46,"receipt_number":"72419","total_price":91.8,"total_price_incl":106.2585,"total_surcharge":0,"taxes":[{"amount":6.426,"id":"b532b2b4-dec4-11ed-8863-0ac98a3b57fb"},{"amount":2.5245,"id":"b532df5a-dec4-11ed-8863-0ac98a3b57fb"},{"amount":5.508,"id":"79a5e97e-17c0-11ee-8863-0ac98a3b57fb"}],"_isEcomOrder":""},{"id":"bd959035-374c-9748-11f0-bcb4c8988b82","outlet_id":"06819b3a-2e91-11ed-f9a0-c4d550292f42","register_id":"06819b3a-2e91-11ed-f9a0-c4d5502c87f5","user_id":"7ff35c1e-54a6-4441-ab36-a5775a7d7d81","customer_id":"0282e8ff-bc1f-11ef-f633-b8bbb494076d","invoice_number":"70088","source":"USER","source_id":null,"complete_open_sequence_id":null,"accounts_transaction_id":null,"has_unsynced_on_account_payments":null,"status":"CLOSED","state":"closed","note":"","short_code":"5f8zgj","return_for":null,"return_ids":[],"total_loyalty":1.82021,"created_at":"2025-11-08T15:16:02+00:00","updated_at":"2025-11-08T15:16:02+00:00","sale_date":"2025-11-08T15:16:02+00:00","deleted_at":null,"line_items":[{"id":"bd959035-374c-9748-11f0-bcb5bd31cc94","product_id":"d0b67012-9894-42de-8651-8c1044b01859","salesperson_id":null,"tax_id":"0ac98a3b-571f-11ee-e863-17c0bf50ac3a","discount_total":0,"discount":0,"price_total":40,"price":40,"cost_total":19,"cost":19,"tax_total":6.3,"tax":6.3,"quantity":1,"loyalty_value":1.2,"note":null,"return_reason":null,"price_set":false,"status":"CONFIRMED","sequence":2,"gift_card_number":null,"tax_components":[{"rate_id":"b532b2b4-dec4-11ed-8863-0ac98a3b57fb","total_tax":2.8},{"rate_id":"b532df5a-dec4-11ed-8863-0ac98a3b57fb","total_tax":1.1},{"rate_id":"79a5e97e-17c0-11ee-8863-0ac98a3b57fb","total_tax":2.4}],"promotions":[],"surcharges":[],"total_tax":6.3,"total_price":40,"unit_discount":0,"unit_price":40,"unit_tax":6.3,"unit_loyalty_value":1.2,"total_cost":19,"total_discount":0,"total_loyalty_value":1.2,"unit_cost":19,"is_return":false},{"id":"bd959035-374c-9748-11f0-bcb5c282a470","product_id":"ab54dc0b-0219-44e0-b839-bde03a5c2c16","salesperson_id":null,"tax_id":"0ac98a3b-571f-11ee-e863-17c0bf50ac3a","discount_total":0,"discount":0,"price_total":28,"price":28,"cost_total":14,"cost":14,"tax_total":4.41,"tax":4.41,"quantity":1,"loyalty_value":0.84,"note":null,"return_reason":null,"price_set":false,"status":"CONFIRMED","sequence":3,"gift_card_number":null,"tax_components":[{"rate_id":"b532b2b4-dec4-11ed-8863-0ac98a3b57fb","total_tax":1.96},{"rate_id":"b532df5a-dec4-11ed-8863-0ac98a3b57fb","total_tax":0.77},{"rate_id":"79a5e97e-17c0-11ee-8863-0ac98a3b57fb","total_tax":1.68}],"promotions":[],"surcharges":[],"total_tax":4.41,"total_price":28,"unit_discount":0,"unit_price":28,"unit_tax":4.41,"unit_loyalty_value":0.84,"total_cost":14,"total_discount":0,"total_loyalty_value":0.84,"unit_cost":14,"is_return":false}],"payments":[{"id":"bd959035-374c-9748-11f0-bcb5d2bfd984","register_id":"06819b3a-2e91-11ed-f9a0-c4d5502c87f5","register_open_sequence_id":"02269032-111f-11f0-fa97-bcb30730a6e0","outlet_id":"06819b3a-2e91-11ed-f9a0-c4d550292f42","retailer_payment_type_id":"caa7892a-6159-4441-80e8-6a27ea6c8960","payment_type_id":"106","name":"Loyalty","amount":8.48,"payment_date":"2025-11-08T15:15:55+00:00","deleted_at":null,"external_attributes":[],"external_applications":[],"surcharge":null,"source_id":null},{"id":"bd959035-374c-9748-11f0-bcb5d57f4cc2","register_id":"06819b3a-2e91-11ed-f9a0-c4d5502c87f5","register_open_sequence_id":"02269032-111f-11f0-fa97-bcb30730a6e0","outlet_id":"06819b3a-2e91-11ed-f9a0-c4d550292f42","retailer_payment_type_id":"a5237779-ff58-4cdc-bdb9-45cc65d6db45","payment_type_id":"1","name":"Cash","amount":80,"payment_date":"2025-11-08T15:16:00+00:00","deleted_at":null,"external_attributes":[],"external_applications":[],"surcharge":null,"source_id":null},{"id":"bd959035-374c-9748-11f0-bcb5d66c625a","register_id":"06819b3a-2e91-11ed-f9a0-c4d5502c87f5","register_open_sequence_id":"02269032-111f-11f0-fa97-bcb30730a6e0","outlet_id":"06819b3a-2e91-11ed-f9a0-c4d550292f42","retailer_payment_type_id":"a5237779-ff58-4cdc-bdb9-45cc65d6db45","payment_type_id":"1","name":"Cash","amount":-9.77,"payment_date":"2025-11-08T15:16:02+00:00","deleted_at":null,"external_attributes":[],"external_applications":[],"surcharge":null,"source_id":null}],"adjustments":[],"external_applications":[],"attributes":[],"version":46991632385,"ecom_custom_charges":{"charges":[],"total":0,"total_tax":0,"total_incl":0},"total_tax":10.71,"receipt_number":"70088","total_price":68,"total_price_incl":78.71,"total_surcharge":0,"taxes":[{"amount":4.76,"id":"b532b2b4-dec4-11ed-8863-0ac98a3b57fb"},{"amount":1.87,"id":"b532df5a-dec4-11ed-8863-0ac98a3b57fb"},{"amount":4.08,"id":"79a5e97e-17c0-11ee-8863-0ac98a3b57fb"}],"_isEcomOrder":""},{"id":"45ed6335-ebcb-a6ad-11f0-a0a3114a8480","outlet_id":"06819b3a-2e91-11ed-f9a0-c4d550292f42","register_id":"06819b3a-2e91-11ed-f9a0-c4d5502c87f5","user_id":"7ff35c1e-54a6-4441-ab36-a5775a7d7d81","customer_id":"0282e8ff-bc1f-11ef-f633-b8bbb494076d","invoice_number":"66093","source":"USER","source_id":null,"complete_open_sequence_id":null,"accounts_transaction_id":null,"has_unsynced_on_account_payments":null,"status":"CLOSED","state":"closed","note":"","short_code":"x3tbzc","return_for":null,"return_ids":[],"total_loyalty":2.4,"created_at":"2025-10-03T21:51:36+00:00","updated_at":"2025-10-04T14:12:53+00:00","sale_date":"2025-10-04T14:12:52+00:00","deleted_at":null,"line_items":[{"id":"45ed6335-ebcb-a6ad-11f0-a0a313abe91c","product_id":"d0b67012-9894-42de-8651-8c1044b01859","salesperson_id":null,"tax_id":"0ac98a3b-571f-11ee-e863-17c0bf50ac3a","discount_total":0,"discount":0,"price_total":40,"price":40,"cost_total":19,"cost":19,"tax_total":6.3,"tax":6.3,"quantity":1,"loyalty_value":1.2,"note":null,"return_reason":null,"price_set":false,"status":"CONFIRMED","sequence":2,"gift_card_number":null,"tax_components":[{"rate_id":"b532b2b4-dec4-11ed-8863-0ac98a3b57fb","total_tax":2.8},{"rate_id":"b532df5a-dec4-11ed-8863-0ac98a3b57fb","total_tax":1.1},{"rate_id":"79a5e97e-17c0-11ee-8863-0ac98a3b57fb","total_tax":2.4}],"promotions":[],"surcharges":[],"total_tax":6.3,"total_price":40,"unit_discount":0,"unit_price":40,"unit_tax":6.3,"unit_loyalty_value":1.2,"total_cost":19,"total_discount":0,"total_loyalty_value":1.2,"unit_cost":19,"is_return":false},{"id":"45ed6335-ebcb-a6ad-11f0-a0a3496bc8a6","product_id":"63d6d6ce-f563-4518-86a9-cc32c6896378","salesperson_id":null,"tax_id":"0ac98a3b-571f-11ee-e863-17c0bf50ac3a","discount_total":0,"discount":0,"price_total":40,"price":40,"cost_total":19,"cost":19,"tax_total":6.3,"tax":6.3,"quantity":1,"loyalty_value":1.2,"note":null,"return_reason":null,"price_set":false,"status":"CONFIRMED","sequence":4,"gift_card_number":null,"tax_components":[{"rate_id":"b532b2b4-dec4-11ed-8863-0ac98a3b57fb","total_tax":2.8},{"rate_id":"b532df5a-dec4-11ed-8863-0ac98a3b57fb","total_tax":1.1},{"rate_id":"79a5e97e-17c0-11ee-8863-0ac98a3b57fb","total_tax":2.4}],"promotions":[],"surcharges":[],"total_tax":6.3,"total_price":40,"unit_discount":0,"unit_price":40,"unit_tax":6.3,"unit_loyalty_value":1.2,"total_cost":19,"total_discount":0,"total_loyalty_value":1.2,"unit_cost":19,"is_return":false}],"payments":[{"id":"45ed6335-ebcb-a6ad-11f0-a12c358a8e7e","register_id":"06819b3a-2e91-11ed-f9a0-c4d5502c87f5","register_open_sequence_id":"02269032-111f-11f0-fa97-a129a161e085","outlet_id":"06819b3a-2e91-11ed-f9a0-c4d550292f42","retailer_payment_type_id":"a5237779-ff58-4cdc-bdb9-45cc65d6db45","payment_type_id":"1","name":"Cash","amount":100,"payment_date":"2025-10-04T14:12:49+00:00","deleted_at":null,"external_attributes":[],"external_applications":[],"surcharge":null,"source_id":null},{"id":"45ed6335-ebcb-a6ad-11f0-a12c3766cc8a","register_id":"06819b3a-2e91-11ed-f9a0-c4d5502c87f5","register_open_sequence_id":"02269032-111f-11f0-fa97-a129a161e085","outlet_id":"06819b3a-2e91-11ed-f9a0-c4d550292f42","retailer_payment_type_id":"a5237779-ff58-4cdc-bdb9-45cc65d6db45","payment_type_id":"1","name":"Cash","amount":-7.4,"payment_date":"2025-10-04T14:12:52+00:00","deleted_at":null,"external_attributes":[],"external_applications":[],"surcharge":null,"source_id":null}],"adjustments":[],"external_applications":[],"attributes":[],"version":46057722135,"ecom_custom_charges":{"charges":[],"total":0,"total_tax":0,"total_incl":0},"total_tax":12.6,"receipt_number":"66093","total_price":80,"total_price_incl":92.6,"total_surcharge":0,"taxes":[{"amount":5.6,"id":"b532b2b4-dec4-11ed-8863-0ac98a3b57fb"},{"amount":2.2,"id":"b532df5a-dec4-11ed-8863-0ac98a3b57fb"},{"amount":4.8,"id":"79a5e97e-17c0-11ee-8863-0ac98a3b57fb"}],"_isEcomOrder":""},{"id":"c7839ea5-939e-998f-11f0-7eb55fca26d4","outlet_id":"06819b3a-2e91-11ed-f9a0-c4d550292f42","register_id":"06819b3a-2e91-11ed-f9a0-c4d5502c87f5","user_id":"7ff35c1e-54a6-4441-ab36-a5775a7d7d81","customer_id":"0282e8ff-bc1f-11ef-f633-b8bbb494076d","invoice_number":"61499","source":"USER","source_id":null,"complete_open_sequence_id":null,"accounts_transaction_id":null,"has_unsynced_on_account_payments":null,"status":"CLOSED","state":"closed","note":"","short_code":"hxzqte","return_for":null,"return_ids":[],"total_loyalty":1.0811,"created_at":"2025-08-21T17:39:29+00:00","updated_at":"2025-08-21T17:39:29+00:00","sale_date":"2025-08-21T17:39:28+00:00","deleted_at":null,"line_items":[{"id":"c7839ea5-939e-998f-11f0-7eb57723b02a","product_id":"cfd02b53-dc1f-4058-962e-fcf8caeaa2e3","salesperson_id":null,"tax_id":"0ac98a3b-571f-11ed-e863-dec4b5327ac2","discount_total":0,"discount":0,"price_total":5.5,"price":5.5,"cost_total":2.5,"cost":2.5,"tax_total":0.53625,"tax":0.53625,"quantity":1,"loyalty_value":0.165,"note":null,"return_reason":null,"price_set":false,"status":"CONFIRMED","sequence":2,"gift_card_number":null,"tax_components":[{"rate_id":"b532b2b4-dec4-11ed-8863-0ac98a3b57fb","total_tax":0.385},{"rate_id":"b532df5a-dec4-11ed-8863-0ac98a3b57fb","total_tax":0.15125}],"promotions":[],"surcharges":[],"total_tax":0.53625,"total_price":5.5,"unit_discount":0,"unit_price":5.5,"unit_tax":0.53625,"unit_loyalty_value":0.165,"total_cost":2.5,"total_discount":0,"total_loyalty_value":0.165,"unit_cost":2.5,"is_return":false},{"id":"c7839ea5-939e-998f-11f0-7eb5a5a1dd8c","product_id":"50258147-ffef-4aab-990d-1625b4d2b577","salesperson_id":null,"tax_id":"0ac98a3b-571f-11ee-e863-17c0bf50ac3a","discount_total":0,"discount":0,"price_total":6,"price":6,"cost_total":3,"cost":3,"tax_total":0.945,"tax":0.945,"quantity":1,"loyalty_value":0.18,"note":null,"return_reason":null,"price_set":false,"status":"CONFIRMED","sequence":3,"gift_card_number":null,"tax_components":[{"rate_id":"b532b2b4-dec4-11ed-8863-0ac98a3b57fb","total_tax":0.42},{"rate_id":"b532df5a-dec4-11ed-8863-0ac98a3b57fb","total_tax":0.165},{"rate_id":"79a5e97e-17c0-11ee-8863-0ac98a3b57fb","total_tax":0.36}],"promotions":[],"surcharges":[],"total_tax":0.945,"total_price":6,"unit_discount":0,"unit_price":6,"unit_tax":0.945,"unit_loyalty_value":0.18,"total_cost":3,"total_discount":0,"total_loyalty_value":0.18,"unit_cost":3,"is_return":false},{"id":"c7839ea5-939e-998f-11f0-7eb5aa2ff8d4","product_id":"f149f78e-3849-414b-a22b-aab7ade3187c","salesperson_id":null,"tax_id":"0ac98a3b-571f-11ee-e863-17c0bf50ac3a","discount_total":0,"discount":0,"price_total":6.5,"price":6.5,"cost_total":3.33,"cost":3.33,"tax_total":1.02375,"tax":1.02375,"quantity":1,"loyalty_value":0.195,"note":null,"return_reason":null,"price_set":false,"status":"CONFIRMED","sequence":4,"gift_card_number":null,"tax_components":[{"rate_id":"b532b2b4-dec4-11ed-8863-0ac98a3b57fb","total_tax":0.455},{"rate_id":"b532df5a-dec4-11ed-8863-0ac98a3b57fb","total_tax":0.17875},{"rate_id":"79a5e97e-17c0-11ee-8863-0ac98a3b57fb","total_tax":0.39}],"promotions":[],"surcharges":[],"total_tax":1.02375,"total_price":6.5,"unit_discount":0,"unit_price":6.5,"unit_tax":1.02375,"unit_loyalty_value":0.195,"total_cost":3.33,"total_discount":0,"total_loyalty_value":0.195,"unit_cost":3.33,"is_return":false},{"id":"c7839ea5-939e-998f-11f0-7eb5abab54ce","product_id":"e9047b81-324e-4b43-882f-29af944c31a1","salesperson_id":null,"tax_id":"0ac98a3b-571f-11ee-e863-17c0bf50ac3a","discount_total":0,"discount":0,"price_total":6.5,"price":6.5,"cost_total":3.33,"cost":3.33,"tax_total":1.02375,"tax":1.02375,"quantity":1,"loyalty_value":0.195,"note":null,"return_reason":null,"price_set":false,"status":"CONFIRMED","sequence":5,"gift_card_number":null,"tax_components":[{"rate_id":"b532b2b4-dec4-11ed-8863-0ac98a3b57fb","total_tax":0.455},{"rate_id":"b532df5a-dec4-11ed-8863-0ac98a3b57fb","total_tax":0.17875},{"rate_id":"79a5e97e-17c0-11ee-8863-0ac98a3b57fb","total_tax":0.39}],"promotions":[],"surcharges":[],"total_tax":1.02375,"total_price":6.5,"unit_discount":0,"unit_price":6.5,"unit_tax":1.02375,"unit_loyalty_value":0.195,"total_cost":3.33,"total_discount":0,"total_loyalty_value":0.195,"unit_cost":3.33,"is_return":false},{"id":"c7839ea5-939e-998f-11f0-7eb5acdb1d66","product_id":"e9047b81-324e-4b43-882f-29af944c31a1","salesperson_id":null,"tax_id":"0ac98a3b-571f-11ee-e863-17c0bf50ac3a","discount_total":0,"discount":0,"price_total":6.5,"price":6.5,"cost_total":3.33,"cost":3.33,"tax_total":1.02375,"tax":1.02375,"quantity":1,"loyalty_value":0.195,"note":null,"return_reason":null,"price_set":false,"status":"CONFIRMED","sequence":6,"gift_card_number":null,"tax_components":[{"rate_id":"b532b2b4-dec4-11ed-8863-0ac98a3b57fb","total_tax":0.455},{"rate_id":"b532df5a-dec4-11ed-8863-0ac98a3b57fb","total_tax":0.17875},{"rate_id":"79a5e97e-17c0-11ee-8863-0ac98a3b57fb","total_tax":0.39}],"promotions":[],"surcharges":[],"total_tax":1.02375,"total_price":6.5,"unit_discount":0,"unit_price":6.5,"unit_tax":1.02375,"unit_loyalty_value":0.195,"total_cost":3.33,"total_discount":0,"total_loyalty_value":0.195,"unit_cost":3.33,"is_return":false},{"id":"c7839ea5-939e-998f-11f0-7eb5ae669c64","product_id":"e9047b81-324e-4b43-882f-29af944c31a1","salesperson_id":null,"tax_id":"0ac98a3b-571f-11ee-e863-17c0bf50ac3a","discount_total":0,"discount":0,"price_total":6.5,"price":6.5,"cost_total":3.33,"cost":3.33,"tax_total":1.02375,"tax":1.02375,"quantity":1,"loyalty_value":0.195,"note":null,"return_reason":null,"price_set":false,"status":"CONFIRMED","sequence":7,"gift_card_number":null,"tax_components":[{"rate_id":"b532b2b4-dec4-11ed-8863-0ac98a3b57fb","total_tax":0.455},{"rate_id":"b532df5a-dec4-11ed-8863-0ac98a3b57fb","total_tax":0.17875},{"rate_id":"79a5e97e-17c0-11ee-8863-0ac98a3b57fb","total_tax":0.39}],"promotions":[],"surcharges":[],"total_tax":1.02375,"total_price":6.5,"unit_discount":0,"unit_price":6.5,"unit_tax":1.02375,"unit_loyalty_value":0.195,"total_cost":3.33,"total_discount":0,"total_loyalty_value":0.195,"unit_cost":3.33,"is_return":false}],"payments":[{"id":"c7839ea5-939e-998f-11f0-7eb5c2ac489a","register_id":"06819b3a-2e91-11ed-f9a0-c4d5502c87f5","register_open_sequence_id":"02269032-111f-11f0-fa97-7e96a9598333","outlet_id":"06819b3a-2e91-11ed-f9a0-c4d550292f42","retailer_payment_type_id":"caa7892a-6159-4441-80e8-6a27ea6c8960","payment_type_id":"106","name":"Loyalty","amount":1.68,"payment_date":"2025-08-21T17:39:16+00:00","deleted_at":null,"external_attributes":[],"external_applications":[],"surcharge":null,"source_id":null},{"id":"c7839ea5-939e-998f-11f0-7eb5c8a3e744","register_id":"06819b3a-2e91-11ed-f9a0-c4d5502c87f5","register_open_sequence_id":"02269032-111f-11f0-fa97-7e96a9598333","outlet_id":"06819b3a-2e91-11ed-f9a0-c4d550292f42","retailer_payment_type_id":"a5237779-ff58-4cdc-bdb9-45cc65d6db45","payment_type_id":"1","name":"Cash","amount":50,"payment_date":"2025-08-21T17:39:26+00:00","deleted_at":null,"external_attributes":[],"external_applications":[],"surcharge":null,"source_id":null},{"id":"c7839ea5-939e-998f-11f0-7eb5c98eccd2","register_id":"06819b3a-2e91-11ed-f9a0-c4d5502c87f5","register_open_sequence_id":"02269032-111f-11f0-fa97-7e96a9598333","outlet_id":"06819b3a-2e91-11ed-f9a0-c4d550292f42","retailer_payment_type_id":"a5237779-ff58-4cdc-bdb9-45cc65d6db45","payment_type_id":"1","name":"Cash","amount":-8.6,"payment_date":"2025-08-21T17:39:28+00:00","deleted_at":null,"external_attributes":[],"external_applications":[],"surcharge":null,"source_id":null}],"adjustments":[],"external_applications":[],"attributes":[],"version":45116688085,"ecom_custom_charges":{"charges":[],"total":0,"total_tax":0,"total_incl":0},"total_tax":5.58,"receipt_number":"61499","total_price":37.5,"total_price_incl":43.07625,"total_surcharge":0,"taxes":[{"amount":2.625,"id":"b532b2b4-dec4-11ed-8863-0ac98a3b57fb"},{"amount":1.03125,"id":"b532df5a-dec4-11ed-8863-0ac98a3b57fb"},{"amount":1.92,"id":"79a5e97e-17c0-11ee-8863-0ac98a3b57fb"}],"_isEcomOrder":""},{"id":"1fb9c4c2-96b3-8624-11f0-479af364a52e","outlet_id":"06819b3a-2e91-11ed-f9a0-c4d550292f42","register_id":"06819b3a-2e91-11ed-f9a0-c4d5502c87f5","user_id":"7ff35c1e-54a6-4441-ab36-a5775a7d7d81","customer_id":"0282e8ff-bc1f-11ef-f633-b8bbb494076d","invoice_number":"54196","source":"USER","source_id":null,"complete_open_sequence_id":null,"accounts_transaction_id":null,"has_unsynced_on_account_payments":null,"status":"CLOSED","state":"closed","note":"","short_code":"u1mwlx","return_for":null,"return_ids":[],"total_loyalty":0.84,"created_at":"2025-06-12T14:56:50+00:00","updated_at":"2025-06-12T14:56:50+00:00","sale_date":"2025-06-12T14:56:49+00:00","deleted_at":null,"line_items":[{"id":"1fb9c4c2-96b3-8624-11f0-479d2d40945e","product_id":"ab54dc0b-0219-44e0-b839-bde03a5c2c16","salesperson_id":null,"tax_id":"0ac98a3b-571f-11ee-e863-17c0bf50ac3a","discount_total":0,"discount":0,"price_total":28,"price":28,"cost_total":14,"cost":14,"tax_total":4.41,"tax":4.41,"quantity":1,"loyalty_value":0.84,"note":null,"return_reason":null,"price_set":false,"status":"CONFIRMED","sequence":2,"gift_card_number":null,"tax_components":[{"rate_id":"b532b2b4-dec4-11ed-8863-0ac98a3b57fb","total_tax":1.96},{"rate_id":"b532df5a-dec4-11ed-8863-0ac98a3b57fb","total_tax":0.77},{"rate_id":"79a5e97e-17c0-11ee-8863-0ac98a3b57fb","total_tax":1.68}],"promotions":[],"surcharges":[],"total_tax":4.41,"total_price":28,"unit_discount":0,"unit_price":28,"unit_tax":4.41,"unit_loyalty_value":0.84,"total_cost":14,"total_discount":0,"total_loyalty_value":0.84,"unit_cost":14,"is_return":false}],"payments":[{"id":"1fb9c4c2-96b3-8624-11f0-479d75f5c2fa","register_id":"06819b3a-2e91-11ed-f9a0-c4d5502c87f5","register_open_sequence_id":"02269032-111f-11f0-eb9a-4794c13eeee0","outlet_id":"06819b3a-2e91-11ed-f9a0-c4d550292f42","retailer_payment_type_id":"a5237779-ff58-4cdc-bdb9-45cc65d6db45","payment_type_id":"1","name":"Cash","amount":40.01,"payment_date":"2025-06-12T14:56:46+00:00","deleted_at":null,"external_attributes":[],"external_applications":[],"surcharge":null,"source_id":null},{"id":"1fb9c4c2-96b3-8624-11f0-479d781920c2","register_id":"06819b3a-2e91-11ed-f9a0-c4d5502c87f5","register_open_sequence_id":"02269032-111f-11f0-eb9a-4794c13eeee0","outlet_id":"06819b3a-2e91-11ed-f9a0-c4d550292f42","retailer_payment_type_id":"a5237779-ff58-4cdc-bdb9-45cc65d6db45","payment_type_id":"1","name":"Cash","amount":-7.6,"payment_date":"2025-06-12T14:56:49+00:00","deleted_at":null,"external_attributes":[],"external_applications":[],"surcharge":null,"source_id":null}],"adjustments":[],"external_applications":[],"attributes":[],"version":43587073815,"ecom_custom_charges":{"charges":[],"total":0,"total_tax":0,"total_incl":0},"total_tax":4.41,"receipt_number":"54196","total_price":28,"total_price_incl":32.41,"total_surcharge":0,"taxes":[{"amount":1.96,"id":"b532b2b4-dec4-11ed-8863-0ac98a3b57fb"},{"amount":0.77,"id":"b532df5a-dec4-11ed-8863-0ac98a3b57fb"},{"amount":1.68,"id":"79a5e97e-17c0-11ee-8863-0ac98a3b57fb"}],"_isEcomOrder":""},{"id":"abfbc28e-fd16-b24f-11f0-4083254537f8","outlet_id":"06819b3a-2e91-11ed-f9a0-c4d550292f42","register_id":"06819b3a-2e91-11ed-f9a0-c4d5502c87f5","user_id":"7ff35c1e-54a6-4441-ab36-a5775a7d7d81","customer_id":"0282e8ff-bc1f-11ef-f633-b8bbb494076d","invoice_number":"53341","source":"USER","source_id":null,"complete_open_sequence_id":null,"accounts_transaction_id":null,"has_unsynced_on_account_payments":null,"status":"CLOSED","state":"closed","note":"","short_code":"hbjfdf","return_for":null,"return_ids":[],"total_loyalty":0.36,"created_at":"2025-06-03T14:06:53+00:00","updated_at":"2025-06-03T14:06:53+00:00","sale_date":"2025-06-03T14:06:52+00:00","deleted_at":null,"line_items":[{"id":"abfbc28e-fd16-b24f-11f0-4083f58e03ae","product_id":"554ecb7b-4227-43ca-b83e-a3384e2739c9","salesperson_id":null,"tax_id":"0ac98a3b-571f-11ed-e863-dec4b5327ac2","discount_total":0,"discount":0,"price_total":12,"price":12,"cost_total":6,"cost":6,"tax_total":1.17,"tax":1.17,"quantity":1,"loyalty_value":0.36,"note":null,"return_reason":null,"price_set":false,"status":"CONFIRMED","sequence":2,"gift_card_number":null,"tax_components":[{"rate_id":"b532b2b4-dec4-11ed-8863-0ac98a3b57fb","total_tax":0.84},{"rate_id":"b532df5a-dec4-11ed-8863-0ac98a3b57fb","total_tax":0.33}],"promotions":[],"surcharges":[],"total_tax":1.17,"total_price":12,"unit_discount":0,"unit_price":12,"unit_tax":1.17,"unit_loyalty_value":0.36,"total_cost":6,"total_discount":0,"total_loyalty_value":0.36,"unit_cost":6,"is_return":false}],"payments":[{"id":"abfbc28e-fd16-b24f-11f0-4083fe4da7e2","register_id":"06819b3a-2e91-11ed-f9a0-c4d5502c87f5","register_open_sequence_id":"02bc0eb6-c81f-11f0-fd4b-4083252d0ed0","outlet_id":"06819b3a-2e91-11ed-f9a0-c4d550292f42","retailer_payment_type_id":"a5237779-ff58-4cdc-bdb9-45cc65d6db45","payment_type_id":"1","name":"Cash","amount":20,"payment_date":"2025-06-03T14:06:49+00:00","deleted_at":null,"external_attributes":[],"external_applications":[],"surcharge":null,"source_id":null},{"id":"abfbc28e-fd16-b24f-11f0-4083fffbd67c","register_id":"06819b3a-2e91-11ed-f9a0-c4d5502c87f5","register_open_sequence_id":"02bc0eb6-c81f-11f0-fd4b-4083252d0ed0","outlet_id":"06819b3a-2e91-11ed-f9a0-c4d550292f42","retailer_payment_type_id":"a5237779-ff58-4cdc-bdb9-45cc65d6db45","payment_type_id":"1","name":"Cash","amount":-6.83,"payment_date":"2025-06-03T14:06:52+00:00","deleted_at":null,"external_attributes":[],"external_applications":[],"surcharge":null,"source_id":null}],"adjustments":[],"external_applications":[],"attributes":[],"version":43402012258,"ecom_custom_charges":{"charges":[],"total":0,"total_tax":0,"total_incl":0},"total_tax":1.17,"receipt_number":"53341","total_price":12,"total_price_incl":13.17,"total_surcharge":0,"taxes":[{"amount":0.84,"id":"b532b2b4-dec4-11ed-8863-0ac98a3b57fb"},{"amount":0.33,"id":"b532df5a-dec4-11ed-8863-0ac98a3b57fb"}],"_isEcomOrder":""},{"id":"b350dcfa-2d6f-b0da-11f0-3bd4b156abc2","outlet_id":"06819b3a-2e91-11ed-f9a0-c4d550292f42","register_id":"06819b3a-2e91-11ed-f9a0-c4d5502c87f5","user_id":"7ff35c1e-54a6-4441-ab36-a5775a7d7d81","customer_id":"0282e8ff-bc1f-11ef-f633-b8bbb494076d","invoice_number":"52753","source":"USER","source_id":null,"complete_open_sequence_id":null,"accounts_transaction_id":null,"has_unsynced_on_account_payments":null,"status":"CLOSED","state":"closed","note":"","short_code":"bpr4cs","return_for":null,"return_ids":[],"total_loyalty":0.36,"created_at":"2025-05-28T15:05:19+00:00","updated_at":"2025-05-28T15:05:19+00:00","sale_date":"2025-05-28T15:05:18+00:00","deleted_at":null,"line_items":[{"id":"b350dcfa-2d6f-b0da-11f0-3bd51c0c9b16","product_id":"0d76603e-a2a1-4519-9e67-fe2a26ad09c2","salesperson_id":null,"tax_id":"0ac98a3b-571f-11ed-e863-dec4b5327ac2","discount_total":0,"discount":0,"price_total":12,"price":12,"cost_total":6,"cost":6,"tax_total":1.17,"tax":1.17,"quantity":1,"loyalty_value":0.36,"note":null,"return_reason":null,"price_set":false,"status":"CONFIRMED","sequence":2,"gift_card_number":null,"tax_components":[{"rate_id":"b532b2b4-dec4-11ed-8863-0ac98a3b57fb","total_tax":0.84},{"rate_id":"b532df5a-dec4-11ed-8863-0ac98a3b57fb","total_tax":0.33}],"promotions":[],"surcharges":[],"total_tax":1.17,"total_price":12,"unit_discount":0,"unit_price":12,"unit_tax":1.17,"unit_loyalty_value":0.36,"total_cost":6,"total_discount":0,"total_loyalty_value":0.36,"unit_cost":6,"is_return":false}],"payments":[{"id":"b350dcfa-2d6f-b0da-11f0-3bd52a67b380","register_id":"06819b3a-2e91-11ed-f9a0-c4d5502c87f5","register_open_sequence_id":"02bc0eb6-c81f-11f0-fd4b-3bcab3d608f2","outlet_id":"06819b3a-2e91-11ed-f9a0-c4d550292f42","retailer_payment_type_id":"a5237779-ff58-4cdc-bdb9-45cc65d6db45","payment_type_id":"1","name":"Cash","amount":13.17,"payment_date":"2025-05-28T15:05:17+00:00","deleted_at":null,"external_attributes":[],"external_applications":[],"surcharge":null,"source_id":null}],"adjustments":[],"external_applications":[],"attributes":[],"version":43290914559,"ecom_custom_charges":{"charges":[],"total":0,"total_tax":0,"total_incl":0},"total_tax":1.17,"receipt_number":"52753","total_price":12,"total_price_incl":13.17,"total_surcharge":0,"taxes":[{"amount":0.84,"id":"b532b2b4-dec4-11ed-8863-0ac98a3b57fb"},{"amount":0.33,"id":"b532df5a-dec4-11ed-8863-0ac98a3b57fb"}],"_isEcomOrder":""},{"id":"b350dcfa-2d6f-b0da-11f0-3bcf30c9e19a","outlet_id":"06819b3a-2e91-11ed-f9a0-c4d550292f42","register_id":"06819b3a-2e91-11ed-f9a0-c4d5502c87f5","user_id":"7ff35c1e-54a6-4441-ab36-a5775a7d7d81","customer_id":"0282e8ff-bc1f-11ef-f633-b8bbb494076d","invoice_number":"52752","source":"USER","source_id":null,"complete_open_sequence_id":null,"accounts_transaction_id":null,"has_unsynced_on_account_payments":null,"status":"CLOSED","state":"closed","note":"","short_code":"lq4kje","return_for":null,"return_ids":[],"total_loyalty":0.11891,"created_at":"2025-05-28T15:01:33+00:00","updated_at":"2025-05-28T15:01:33+00:00","sale_date":"2025-05-28T15:01:33+00:00","deleted_at":null,"line_items":[{"id":"b350dcfa-2d6f-b0da-11f0-3bd4427c91d0","product_id":"47e4ac86-2fdf-4f7b-bf9e-137a618798e6","salesperson_id":null,"tax_id":"0ac98a3b-571f-11ee-e863-17c0bf50ac3a","discount_total":0,"discount":0,"price_total":5,"price":5,"cost_total":2.5,"cost":2.5,"tax_total":0.7875,"tax":0.7875,"quantity":1,"loyalty_value":0.15,"note":null,"return_reason":null,"price_set":false,"status":"CONFIRMED","sequence":2,"gift_card_number":null,"tax_components":[{"rate_id":"b532b2b4-dec4-11ed-8863-0ac98a3b57fb","total_tax":0.35},{"rate_id":"b532df5a-dec4-11ed-8863-0ac98a3b57fb","total_tax":0.1375},{"rate_id":"79a5e97e-17c0-11ee-8863-0ac98a3b57fb","total_tax":0.3}],"promotions":[],"surcharges":[],"total_tax":0.7875,"total_price":5,"unit_discount":0,"unit_price":5,"unit_tax":0.7875,"unit_loyalty_value":0.15,"total_cost":2.5,"total_discount":0,"total_loyalty_value":0.15,"unit_cost":2.5,"is_return":false}],"payments":[{"id":"b350dcfa-2d6f-b0da-11f0-3bd49a1a4306","register_id":"06819b3a-2e91-11ed-f9a0-c4d5502c87f5","register_open_sequence_id":"02bc0eb6-c81f-11f0-fd4b-3bcab3d608f2","outlet_id":"06819b3a-2e91-11ed-f9a0-c4d550292f42","retailer_payment_type_id":"caa7892a-6159-4441-80e8-6a27ea6c8960","payment_type_id":"106","name":"Loyalty","amount":1.2,"payment_date":"2025-05-28T15:01:15+00:00","deleted_at":null,"external_attributes":[],"external_applications":[],"surcharge":null,"source_id":null},{"id":"b350dcfa-2d6f-b0da-11f0-3bd4a3286928","register_id":"06819b3a-2e91-11ed-f9a0-c4d5502c87f5","register_open_sequence_id":"02bc0eb6-c81f-11f0-fd4b-3bcab3d608f2","outlet_id":"06819b3a-2e91-11ed-f9a0-c4d550292f42","retailer_payment_type_id":"a5237779-ff58-4cdc-bdb9-45cc65d6db45","payment_type_id":"1","name":"Cash","amount":20,"payment_date":"2025-05-28T15:01:30+00:00","deleted_at":null,"external_attributes":[],"external_applications":[],"surcharge":null,"source_id":null},{"id":"b350dcfa-2d6f-b0da-11f0-3bd4a4ce7e2a","register_id":"06819b3a-2e91-11ed-f9a0-c4d5502c87f5","register_open_sequence_id":"02bc0eb6-c81f-11f0-fd4b-3bcab3d608f2","outlet_id":"06819b3a-2e91-11ed-f9a0-c4d550292f42","retailer_payment_type_id":"a5237779-ff58-4cdc-bdb9-45cc65d6db45","payment_type_id":"1","name":"Cash","amount":-15.41,"payment_date":"2025-05-28T15:01:33+00:00","deleted_at":null,"external_attributes":[],"external_applications":[],"surcharge":null,"source_id":null}],"adjustments":[],"external_applications":[],"attributes":[],"version":43290847307,"ecom_custom_charges":{"charges":[],"total":0,"total_tax":0,"total_incl":0},"total_tax":0.79,"receipt_number":"52752","total_price":5,"total_price_incl":5.7875,"total_surcharge":0,"taxes":[{"amount":0.35,"id":"b532b2b4-dec4-11ed-8863-0ac98a3b57fb"},{"amount":0.1375,"id":"b532df5a-dec4-11ed-8863-0ac98a3b57fb"},{"amount":0.3,"id":"79a5e97e-17c0-11ee-8863-0ac98a3b57fb"}],"_isEcomOrder":""},{"id":"5d9d4dee-ba94-abe6-11ef-b8baab6c13f2","outlet_id":"06819b3a-2e91-11ed-f9a0-c4d550292f42","register_id":"06819b3a-2e91-11ed-f9a0-c4d5502c87f5","user_id":"71bd9f52-ced2-4397-b7ff-afaa511b8fc5","customer_id":"0282e8ff-bc1f-11ef-f633-b8bbb494076d","invoice_number":"38749","source":"USER","source_id":null,"complete_open_sequence_id":null,"accounts_transaction_id":null,"has_unsynced_on_account_payments":null,"status":"CLOSED","state":"closed","note":"New girl","short_code":"f1nl2y","return_for":null,"return_ids":[],"total_loyalty":1.2,"created_at":"2024-12-12T19:04:02+00:00","updated_at":"2024-12-12T19:04:02+00:00","sale_date":"2024-12-12T19:04:01+00:00","deleted_at":null,"line_items":[{"id":"5d9d4dee-ba94-abe6-11ef-b8baab7727c4","product_id":"06819b3a-2e1f-11ed-f9a0-c4d5522bf959","salesperson_id":null,"tax_id":"06819b3a-2e91-11ed-f9a0-c4d5502316f5","discount_total":0,"discount":0,"price_total":-4,"price":4,"cost_total":0,"cost":0,"tax_total":-0.39,"tax":0.39,"quantity":-1,"loyalty_value":0,"note":null,"return_reason":null,"price_set":false,"status":"CONFIRMED","sequence":3,"gift_card_number":null,"tax_components":[{"rate_id":"b532b2b4-dec4-11ed-8863-0ac98a3b57fb","total_tax":-0.28},{"rate_id":"b532df5a-dec4-11ed-8863-0ac98a3b57fb","total_tax":-0.11}],"promotions":[],"surcharges":[],"total_tax":-0.39,"total_price":-4,"unit_discount":0,"unit_price":4,"unit_tax":0.39,"unit_loyalty_value":0,"total_cost":0,"total_discount":0,"total_loyalty_value":0,"unit_cost":0,"is_return":false},{"id":"5d9d4dee-ba94-abe6-11ef-b8bbc6b50708","product_id":"64940e1d-0f98-4e1d-902d-37a63c985e5d","salesperson_id":null,"tax_id":"0ac98a3b-571f-11ed-e863-dec4b5327ac2","discount_total":0,"discount":0,"price_total":40,"price":40,"cost_total":20,"cost":20,"tax_total":3.9,"tax":3.9,"quantity":1,"loyalty_value":1.2,"note":null,"return_reason":null,"price_set":false,"status":"CONFIRMED","sequence":2,"gift_card_number":null,"tax_components":[{"rate_id":"b532b2b4-dec4-11ed-8863-0ac98a3b57fb","total_tax":2.8},{"rate_id":"b532df5a-dec4-11ed-8863-0ac98a3b57fb","total_tax":1.1}],"promotions":[],"surcharges":[],"total_tax":3.9,"total_price":40,"unit_discount":0,"unit_price":40,"unit_tax":3.9,"unit_loyalty_value":1.2,"total_cost":20,"total_discount":0,"total_loyalty_value":1.2,"unit_cost":20,"is_return":false}],"payments":[{"id":"5d9d4dee-ba94-abe6-11ef-b8bbd78ae8a4","register_id":"06819b3a-2e91-11ed-f9a0-c4d5502c87f5","register_open_sequence_id":"0282e8ff-bc1f-11ef-f633-b8a1dd9abcd1","outlet_id":"06819b3a-2e91-11ed-f9a0-c4d550292f42","retailer_payment_type_id":"a5237779-ff58-4cdc-bdb9-45cc65d6db45","payment_type_id":"1","name":"Cash","amount":40,"payment_date":"2024-12-12T19:03:58+00:00","deleted_at":null,"external_attributes":[],"external_applications":[],"surcharge":null,"source_id":null},{"id":"5d9d4dee-ba94-abe6-11ef-b8bbd93b725e","register_id":"06819b3a-2e91-11ed-f9a0-c4d5502c87f5","register_open_sequence_id":"0282e8ff-bc1f-11ef-f633-b8a1dd9abcd1","outlet_id":"06819b3a-2e91-11ed-f9a0-c4d550292f42","retailer_payment_type_id":"a5237779-ff58-4cdc-bdb9-45cc65d6db45","payment_type_id":"1","name":"Cash","amount":-0.49,"payment_date":"2024-12-12T19:04:01+00:00","deleted_at":null,"external_attributes":[],"external_applications":[],"surcharge":null,"source_id":null}],"adjustments":[],"external_applications":[],"attributes":[],"version":39808996234,"ecom_custom_charges":{"charges":[],"total":0,"total_tax":0,"total_incl":0},"total_tax":3.51,"receipt_number":"38749","total_price":36,"total_price_incl":39.51,"total_surcharge":0,"taxes":[{"amount":2.52,"id":"b532b2b4-dec4-11ed-8863-0ac98a3b57fb"},{"amount":0.99,"id":"b532df5a-dec4-11ed-8863-0ac98a3b57fb"}],"_isEcomOrder":false}],"cachedAt":"2026-01-15T17:29:02.294Z"}