{"customerId":"0ac98a3b-571f-11ee-e541-84a6135559dd","sales":[{"id":"0ac98a3b-571f-11ee-e541-a3a34a5631b9","outlet_id":"06819b3a-2e91-11ed-f9a0-c4d550292f42","register_id":"0ac98a3b-571f-11ed-e863-e388edc42ddd","user_id":"06819b3a-2e91-11ed-f9a0-c4d5502e3deb","customer_id":"0ac98a3b-571f-11ee-e541-84a6135559dd","invoice_number":"39","source":"ecw:16E930E1F50F9000","source_id":"43","complete_open_sequence_id":null,"accounts_transaction_id":null,"has_unsynced_on_account_payments":null,"status":"PICKED_UP_CLOSED","state":"closed","note":"Order ID:43\n\nPickup time:\nTue, Dec 26, 2023, 11:00 AM\n\nTotal Discount Amount: 0","short_code":"autysl","return_for":null,"return_ids":[],"total_loyalty":1.695,"created_at":"2023-12-26T04:00:21+00:00","updated_at":"2023-12-26T15:51:59+00:00","sale_date":"2023-12-26T04:00:18+00:00","deleted_at":null,"line_items":[{"id":"255127d9-4785-48e8-9ce1-e9b6968874df","product_id":"ac3b28a4-c3a6-4d4d-814d-e95452bcfa99","salesperson_id":null,"tax_id":"0ac98a3b-571f-11ee-e863-17c0bf50ac3a","discount_total":0,"discount":0,"price_total":5.5,"price":2.75,"cost_total":2.52,"cost":1.26,"tax_total":0.86626,"tax":0.43313,"quantity":2,"loyalty_value":0.0825,"note":null,"return_reason":null,"price_set":false,"status":"CONFIRMED","sequence":0,"gift_card_number":null,"tax_components":[{"rate_id":"b532b2b4-dec4-11ed-8863-0ac98a3b57fb","total_tax":0.385},{"rate_id":"b532df5a-dec4-11ed-8863-0ac98a3b57fb","total_tax":0.15125},{"rate_id":"79a5e97e-17c0-11ee-8863-0ac98a3b57fb","total_tax":0.33}],"promotions":[],"surcharges":[],"total_tax":0.86626,"total_price":5.5,"unit_discount":0,"unit_price":2.75,"unit_tax":0.43313,"unit_loyalty_value":0.0825,"total_cost":2.52,"total_discount":0,"total_loyalty_value":0.165,"unit_cost":1.26,"is_return":false},{"id":"6f4c057b-9a75-40c7-9554-74a9ed408ecc","product_id":"2c2f93b7-cff2-4d41-acd4-c59a4e8d5b5f","salesperson_id":null,"tax_id":"0ac98a3b-571f-11ee-e863-17c0bf50ac3a","discount_total":0,"discount":0,"price_total":35,"price":35,"cost_total":17,"cost":17,"tax_total":5.5125,"tax":5.5125,"quantity":1,"loyalty_value":1.05,"note":null,"return_reason":null,"price_set":false,"status":"CONFIRMED","sequence":0,"gift_card_number":null,"tax_components":[{"rate_id":"b532b2b4-dec4-11ed-8863-0ac98a3b57fb","total_tax":2.45},{"rate_id":"b532df5a-dec4-11ed-8863-0ac98a3b57fb","total_tax":0.9625},{"rate_id":"79a5e97e-17c0-11ee-8863-0ac98a3b57fb","total_tax":2.1}],"promotions":[],"surcharges":[],"total_tax":5.5125,"total_price":35,"unit_discount":0,"unit_price":35,"unit_tax":5.5125,"unit_loyalty_value":1.05,"total_cost":17,"total_discount":0,"total_loyalty_value":1.05,"unit_cost":17,"is_return":false},{"id":"f09b3e1b-ce85-4251-a7b5-eb749b34d8b5","product_id":"0a9216fc-3001-4527-968b-aba036a26f2c","salesperson_id":null,"tax_id":"0ac98a3b-571f-11ee-e863-17c0bf50ac3a","discount_total":0,"discount":0,"price_total":16,"price":16,"cost_total":8,"cost":8,"tax_total":2.52,"tax":2.52,"quantity":1,"loyalty_value":0.48,"note":null,"return_reason":null,"price_set":false,"status":"CONFIRMED","sequence":0,"gift_card_number":null,"tax_components":[{"rate_id":"b532b2b4-dec4-11ed-8863-0ac98a3b57fb","total_tax":1.12},{"rate_id":"b532df5a-dec4-11ed-8863-0ac98a3b57fb","total_tax":0.44},{"rate_id":"79a5e97e-17c0-11ee-8863-0ac98a3b57fb","total_tax":0.96}],"promotions":[],"surcharges":[],"total_tax":2.52,"total_price":16,"unit_discount":0,"unit_price":16,"unit_tax":2.52,"unit_loyalty_value":0.48,"total_cost":8,"total_discount":0,"total_loyalty_value":0.48,"unit_cost":8,"is_return":false}],"payments":[{"id":"0ac98a3b-571f-11ee-e541-a3a34a80434b","register_id":"0ac98a3b-571f-11ed-e863-e388edc42ddd","register_open_sequence_id":"0ac98a3b-571f-11ee-e541-a01a8606e9e0","outlet_id":"06819b3a-2e91-11ed-f9a0-c4d550292f42","retailer_payment_type_id":"22c93c97-c8c1-458b-b73a-402f761cce73","payment_type_id":"171","name":"Square (Online)","amount":65.4,"payment_date":"2023-12-26T04:00:18+00:00","deleted_at":null,"external_attributes":[],"external_applications":[],"surcharge":null,"source_id":null}],"adjustments":[],"external_applications":[],"attributes":["pickup"],"version":33359026169,"ecom_custom_charges":{"charges":[],"total":0,"total_tax":0,"total_incl":0},"total_tax":8.9,"receipt_number":"39","total_price":56.5,"total_price_incl":65.39876,"total_surcharge":0,"taxes":[{"amount":3.955,"id":"b532b2b4-dec4-11ed-8863-0ac98a3b57fb"},{"amount":1.55375,"id":"b532df5a-dec4-11ed-8863-0ac98a3b57fb"},{"amount":3.39,"id":"79a5e97e-17c0-11ee-8863-0ac98a3b57fb"}],"_isEcomOrder":true},{"id":"0ac98a3b-571f-11ee-e541-84a613789710","outlet_id":"06819b3a-2e91-11ed-f9a0-c4d550292f42","register_id":"0ac98a3b-571f-11ed-e863-e388edc42ddd","user_id":"06819b3a-2e91-11ed-f9a0-c4d5502e3deb","customer_id":"0ac98a3b-571f-11ee-e541-84a6135559dd","invoice_number":"26","source":"ecw:16E930E1F50F9000","source_id":"30","complete_open_sequence_id":null,"accounts_transaction_id":null,"has_unsynced_on_account_payments":null,"status":"PICKED_UP_CLOSED","state":"closed","note":"Order ID:30\n\nPickup time:\nThu, Nov 16, 2023, 12:10 PM\n\nTotal Discount Amount: 0","short_code":"oxspsh","return_for":null,"return_ids":[],"total_loyalty":1.05,"created_at":"2023-11-16T17:32:12+00:00","updated_at":"2023-11-16T17:43:50+00:00","sale_date":"2023-11-16T17:32:08+00:00","deleted_at":null,"line_items":[{"id":"da473767-764e-4039-8466-45c517bfcc45","product_id":"2c2f93b7-cff2-4d41-acd4-c59a4e8d5b5f","salesperson_id":null,"tax_id":"0ac98a3b-571f-11ee-e863-17c0bf50ac3a","discount_total":0,"discount":0,"price_total":35,"price":35,"cost_total":17,"cost":17,"tax_total":5.5125,"tax":5.5125,"quantity":1,"loyalty_value":1.05,"note":null,"return_reason":null,"price_set":false,"status":"CONFIRMED","sequence":0,"gift_card_number":null,"tax_components":[{"rate_id":"b532b2b4-dec4-11ed-8863-0ac98a3b57fb","total_tax":2.45},{"rate_id":"b532df5a-dec4-11ed-8863-0ac98a3b57fb","total_tax":0.9625},{"rate_id":"79a5e97e-17c0-11ee-8863-0ac98a3b57fb","total_tax":2.1}],"promotions":[],"surcharges":[],"total_tax":5.5125,"total_price":35,"unit_discount":0,"unit_price":35,"unit_tax":5.5125,"unit_loyalty_value":1.05,"total_cost":17,"total_discount":0,"total_loyalty_value":1.05,"unit_cost":17,"is_return":false}],"payments":[{"id":"0ac98a3b-571f-11ee-e541-84a6139d2e53","register_id":"0ac98a3b-571f-11ed-e863-e388edc42ddd","register_open_sequence_id":"0ac98a3b-571f-11ee-e541-84a613827d6d","outlet_id":"06819b3a-2e91-11ed-f9a0-c4d550292f42","retailer_payment_type_id":"22c93c97-c8c1-458b-b73a-402f761cce73","payment_type_id":"171","name":"Square (Online)","amount":40.51,"payment_date":"2023-11-16T17:32:08+00:00","deleted_at":null,"external_attributes":[],"external_applications":[],"surcharge":null,"source_id":null}],"adjustments":[],"external_applications":[],"attributes":["pickup"],"version":36948417794,"ecom_custom_charges":{"charges":[],"total":0,"total_tax":0,"total_incl":0},"total_tax":5.51,"receipt_number":"26","total_price":35,"total_price_incl":40.5125,"total_surcharge":0,"taxes":[{"amount":2.45,"id":"b532b2b4-dec4-11ed-8863-0ac98a3b57fb"},{"amount":0.9625,"id":"b532df5a-dec4-11ed-8863-0ac98a3b57fb"},{"amount":2.1,"id":"79a5e97e-17c0-11ee-8863-0ac98a3b57fb"}],"_isEcomOrder":true}],"cachedAt":"2026-01-15T17:19:58.015Z"}