{"customerId":"0200a133-d11f-11ef-e3f5-5120b2d87e30","sales":[{"id":"e3e4e0ee-76f2-9c2b-11f0-642408c8e754","outlet_id":"06819b3a-2e91-11ed-f9a0-c4d550292f42","register_id":"06819b3a-2e91-11ed-f9a0-c4d5502c87f5","user_id":"3c2d6f1d-c7ac-4f14-ba6e-664ab51f8000","customer_id":"0200a133-d11f-11ef-e3f5-5120b2d87e30","invoice_number":"57908","source":"USER","source_id":null,"complete_open_sequence_id":null,"accounts_transaction_id":null,"has_unsynced_on_account_payments":null,"status":"CLOSED","state":"closed","note":"","short_code":"joesh3","return_for":null,"return_ids":[],"total_loyalty":1.54187,"created_at":"2025-07-18T22:14:51+00:00","updated_at":"2025-07-18T22:14:51+00:00","sale_date":"2025-07-18T22:14:50+00:00","deleted_at":null,"line_items":[{"id":"e3e4e0ee-76f2-9c2b-11f0-64246fb14f7e","product_id":"4c7fd054-36c7-4062-bca9-3ed5dfd497d2","salesperson_id":null,"tax_id":"0ac98a3b-571f-11ed-e863-dec4b5327ac2","discount_total":0,"discount":0,"price_total":9,"price":9,"cost_total":3.8,"cost":3.8,"tax_total":0.8775,"tax":0.8775,"quantity":1,"loyalty_value":0.27,"note":null,"return_reason":null,"price_set":false,"status":"CONFIRMED","sequence":2,"gift_card_number":null,"tax_components":[{"rate_id":"b532b2b4-dec4-11ed-8863-0ac98a3b57fb","total_tax":0.63},{"rate_id":"b532df5a-dec4-11ed-8863-0ac98a3b57fb","total_tax":0.2475}],"promotions":[],"surcharges":[],"total_tax":0.8775,"total_price":9,"unit_discount":0,"unit_price":9,"unit_tax":0.8775,"unit_loyalty_value":0.27,"total_cost":3.8,"total_discount":0,"total_loyalty_value":0.27,"unit_cost":3.8,"is_return":false},{"id":"e3e4e0ee-76f2-9c2b-11f0-6424886f2694","product_id":"290b2d3b-ae05-4c8a-8f2b-c1c9950cc17c","salesperson_id":null,"tax_id":"0ac98a3b-571f-11ed-e863-dec4b5327ac2","discount_total":-7,"discount":-7,"price_total":7,"price":7,"cost_total":0,"cost":0,"tax_total":0.6825,"tax":0.6825,"quantity":1,"loyalty_value":0.21,"note":"Wax pick","return_reason":null,"price_set":true,"status":"CONFIRMED","sequence":3,"gift_card_number":null,"tax_components":[{"rate_id":"b532b2b4-dec4-11ed-8863-0ac98a3b57fb","total_tax":0.49},{"rate_id":"b532df5a-dec4-11ed-8863-0ac98a3b57fb","total_tax":0.1925}],"promotions":[],"surcharges":[],"total_tax":0.6825,"total_price":7,"unit_discount":-7,"unit_price":7,"unit_tax":0.6825,"unit_loyalty_value":0.21,"total_cost":0,"total_discount":-7,"total_loyalty_value":0.21,"unit_cost":0,"is_return":false},{"id":"e3e4e0ee-76f2-9c2b-11f0-64249319b55a","product_id":"bd18fe13-d76e-43f4-a93a-e9595f9378eb","salesperson_id":null,"tax_id":"0ac98a3b-571f-11ee-e863-17c0bf50ac3a","discount_total":0,"discount":0,"price_total":40,"price":40,"cost_total":20,"cost":20,"tax_total":6.3,"tax":6.3,"quantity":1,"loyalty_value":1.2,"note":null,"return_reason":null,"price_set":false,"status":"CONFIRMED","sequence":4,"gift_card_number":null,"tax_components":[{"rate_id":"b532b2b4-dec4-11ed-8863-0ac98a3b57fb","total_tax":2.8},{"rate_id":"b532df5a-dec4-11ed-8863-0ac98a3b57fb","total_tax":1.1},{"rate_id":"79a5e97e-17c0-11ee-8863-0ac98a3b57fb","total_tax":2.4}],"promotions":[],"surcharges":[],"total_tax":6.3,"total_price":40,"unit_discount":0,"unit_price":40,"unit_tax":6.3,"unit_loyalty_value":1.2,"total_cost":20,"total_discount":0,"total_loyalty_value":1.2,"unit_cost":20,"is_return":false}],"payments":[{"id":"e3e4e0ee-76f2-9c2b-11f0-6424756ba25c","register_id":"06819b3a-2e91-11ed-f9a0-c4d5502c87f5","register_open_sequence_id":"02269032-111f-11f0-eb9a-63de056b0751","outlet_id":"06819b3a-2e91-11ed-f9a0-c4d550292f42","retailer_payment_type_id":"caa7892a-6159-4441-80e8-6a27ea6c8960","payment_type_id":"106","name":"Loyalty","amount":5.25,"payment_date":"2025-07-18T22:13:40+00:00","deleted_at":null,"external_attributes":[],"external_applications":[],"surcharge":null,"source_id":null},{"id":"e3e4e0ee-76f2-9c2b-11f0-64249ede85d2","register_id":"06819b3a-2e91-11ed-f9a0-c4d5502c87f5","register_open_sequence_id":"02269032-111f-11f0-eb9a-63de056b0751","outlet_id":"06819b3a-2e91-11ed-f9a0-c4d550292f42","retailer_payment_type_id":"a5237779-ff58-4cdc-bdb9-45cc65d6db45","payment_type_id":"1","name":"Cash","amount":58.61,"payment_date":"2025-07-18T22:14:49+00:00","deleted_at":null,"external_attributes":[],"external_applications":[],"surcharge":null,"source_id":null}],"adjustments":[],"external_applications":[],"attributes":[],"version":44338659226,"ecom_custom_charges":{"charges":[],"total":0,"total_tax":0,"total_incl":0},"total_tax":7.86,"receipt_number":"57908","total_price":56,"total_price_incl":63.86,"total_surcharge":0,"taxes":[{"amount":3.92,"id":"b532b2b4-dec4-11ed-8863-0ac98a3b57fb"},{"amount":1.54,"id":"b532df5a-dec4-11ed-8863-0ac98a3b57fb"},{"amount":2.4,"id":"79a5e97e-17c0-11ee-8863-0ac98a3b57fb"}],"_isEcomOrder":""},{"id":"d575ad82-4f98-ba77-11f0-1254cadca456","outlet_id":"06819b3a-2e91-11ed-f9a0-c4d550292f42","register_id":"06819b3a-2e91-11ed-f9a0-c4d5502c87f5","user_id":"7ff35c1e-54a6-4441-ab36-a5775a7d7d81","customer_id":"0200a133-d11f-11ef-e3f5-5120b2d87e30","invoice_number":"48054","source":"USER","source_id":null,"complete_open_sequence_id":null,"accounts_transaction_id":null,"has_unsynced_on_account_payments":null,"status":"CLOSED","state":"closed","note":"","short_code":"8o7wxm","return_for":null,"return_ids":[],"total_loyalty":2.3547,"created_at":"2025-04-05T19:35:24+00:00","updated_at":"2025-04-05T19:35:24+00:00","sale_date":"2025-04-05T19:35:24+00:00","deleted_at":null,"line_items":[{"id":"d575ad82-4f98-ba77-11f0-125507c2e934","product_id":"c45e58b5-b091-4299-b0cf-c68ca2eccc78","salesperson_id":null,"tax_id":"0ac98a3b-571f-11ee-e863-17c0bf50ac3a","discount_total":4,"discount":4,"price_total":36,"price":36,"cost_total":20,"cost":20,"tax_total":5.67,"tax":5.67,"quantity":1,"loyalty_value":1.08,"note":"Opened","return_reason":null,"price_set":true,"status":"CONFIRMED","sequence":2,"gift_card_number":null,"tax_components":[{"rate_id":"b532b2b4-dec4-11ed-8863-0ac98a3b57fb","total_tax":2.52},{"rate_id":"b532df5a-dec4-11ed-8863-0ac98a3b57fb","total_tax":0.99},{"rate_id":"79a5e97e-17c0-11ee-8863-0ac98a3b57fb","total_tax":2.16}],"promotions":[],"surcharges":[],"total_tax":5.67,"total_price":36,"unit_discount":4,"unit_price":36,"unit_tax":5.67,"unit_loyalty_value":1.08,"total_cost":20,"total_discount":4,"total_loyalty_value":1.08,"unit_cost":20,"is_return":false},{"id":"d575ad82-4f98-ba77-11f0-125510b57160","product_id":"a754d5b8-bdad-4771-9627-aa7698967f2d","salesperson_id":null,"tax_id":"0ac98a3b-571f-11ee-e863-17c0bf50ac3a","discount_total":0,"discount":0,"price_total":40,"price":40,"cost_total":20,"cost":20,"tax_total":6.3,"tax":6.3,"quantity":1,"loyalty_value":1.2,"note":null,"return_reason":null,"price_set":false,"status":"CONFIRMED","sequence":3,"gift_card_number":null,"tax_components":[{"rate_id":"b532b2b4-dec4-11ed-8863-0ac98a3b57fb","total_tax":2.8},{"rate_id":"b532df5a-dec4-11ed-8863-0ac98a3b57fb","total_tax":1.1},{"rate_id":"79a5e97e-17c0-11ee-8863-0ac98a3b57fb","total_tax":2.4}],"promotions":[],"surcharges":[],"total_tax":6.3,"total_price":40,"unit_discount":0,"unit_price":40,"unit_tax":6.3,"unit_loyalty_value":1.2,"total_cost":20,"total_discount":0,"total_loyalty_value":1.2,"unit_cost":20,"is_return":false},{"id":"d575ad82-4f98-ba77-11f0-125514a34c34","product_id":"fcb34cfa-e958-49a6-9776-5ca64da41642","salesperson_id":null,"tax_id":"0ac98a3b-571f-11ed-e863-dec4b5327ac2","discount_total":0,"discount":0,"price_total":2.49,"price":2.49,"cost_total":0.77,"cost":0.77,"tax_total":0.24278,"tax":0.24278,"quantity":1,"loyalty_value":0.0747,"note":null,"return_reason":null,"price_set":false,"status":"CONFIRMED","sequence":4,"gift_card_number":null,"tax_components":[{"rate_id":"b532b2b4-dec4-11ed-8863-0ac98a3b57fb","total_tax":0.1743},{"rate_id":"b532df5a-dec4-11ed-8863-0ac98a3b57fb","total_tax":0.06848}],"promotions":[],"surcharges":[],"total_tax":0.24278,"total_price":2.49,"unit_discount":0,"unit_price":2.49,"unit_tax":0.24278,"unit_loyalty_value":0.0747,"total_cost":0.77,"total_discount":0,"total_loyalty_value":0.0747,"unit_cost":0.77,"is_return":false}],"payments":[{"id":"d575ad82-4f98-ba77-11f0-12551dc00a78","register_id":"06819b3a-2e91-11ed-f9a0-c4d5502c87f5","register_open_sequence_id":"0282e8ff-bc1f-11f0-f633-122d7b95bfb2","outlet_id":"06819b3a-2e91-11ed-f9a0-c4d550292f42","retailer_payment_type_id":"a5237779-ff58-4cdc-bdb9-45cc65d6db45","payment_type_id":"1","name":"Cash","amount":90.7,"payment_date":"2025-04-05T19:35:22+00:00","deleted_at":null,"external_attributes":[],"external_applications":[],"surcharge":null,"source_id":null}],"adjustments":[],"external_applications":[],"attributes":[],"version":42285883528,"ecom_custom_charges":{"charges":[],"total":0,"total_tax":0,"total_incl":0},"total_tax":12.21,"receipt_number":"48054","total_price":78.49,"total_price_incl":90.70278,"total_surcharge":0,"taxes":[{"amount":5.4943,"id":"b532b2b4-dec4-11ed-8863-0ac98a3b57fb"},{"amount":2.15848,"id":"b532df5a-dec4-11ed-8863-0ac98a3b57fb"},{"amount":4.56,"id":"79a5e97e-17c0-11ee-8863-0ac98a3b57fb"}],"_isEcomOrder":""},{"id":"c503ac82-f273-804a-11f0-02a7a6577ab4","outlet_id":"06819b3a-2e91-11ed-f9a0-c4d550292f42","register_id":"06819b3a-2e91-11ed-f9a0-c4d5502c87f5","user_id":"71bd9f52-ced2-4397-b7ff-afaa511b8fc5","customer_id":"0200a133-d11f-11ef-e3f5-5120b2d87e30","invoice_number":"46227","source":"USER","source_id":null,"complete_open_sequence_id":null,"accounts_transaction_id":null,"has_unsynced_on_account_payments":null,"status":"CLOSED","state":"closed","note":"","short_code":"yoaw0l","return_for":null,"return_ids":[],"total_loyalty":2.8903,"created_at":"2025-03-16T20:49:51+00:00","updated_at":"2025-03-16T20:49:51+00:00","sale_date":"2025-03-16T20:49:50+00:00","deleted_at":null,"line_items":[{"id":"c503ac82-f273-804a-11f0-02a80123083c","product_id":"73b77959-0fe4-4c47-ba28-0bd63400a49c","salesperson_id":null,"tax_id":"0ac98a3b-571f-11ee-e863-17c0bf50ac3a","discount_total":0,"discount":0,"price_total":40,"price":40,"cost_total":20,"cost":20,"tax_total":6.3,"tax":6.3,"quantity":1,"loyalty_value":1.2,"note":null,"return_reason":null,"price_set":false,"status":"CONFIRMED","sequence":2,"gift_card_number":null,"tax_components":[{"rate_id":"b532b2b4-dec4-11ed-8863-0ac98a3b57fb","total_tax":2.8},{"rate_id":"b532df5a-dec4-11ed-8863-0ac98a3b57fb","total_tax":1.1},{"rate_id":"79a5e97e-17c0-11ee-8863-0ac98a3b57fb","total_tax":2.4}],"promotions":[],"surcharges":[],"total_tax":6.3,"total_price":40,"unit_discount":0,"unit_price":40,"unit_tax":6.3,"unit_loyalty_value":1.2,"total_cost":20,"total_discount":0,"total_loyalty_value":1.2,"unit_cost":20,"is_return":false},{"id":"c503ac82-f273-804a-11f0-02a803b22056","product_id":"d7293bf2-5024-42ff-8fcb-84e1f5392e22","salesperson_id":null,"tax_id":"0ac98a3b-571f-11ee-e863-17c0bf50ac3a","discount_total":0,"discount":0,"price_total":40,"price":40,"cost_total":20,"cost":20,"tax_total":6.3,"tax":6.3,"quantity":1,"loyalty_value":1.2,"note":null,"return_reason":null,"price_set":false,"status":"CONFIRMED","sequence":3,"gift_card_number":null,"tax_components":[{"rate_id":"b532b2b4-dec4-11ed-8863-0ac98a3b57fb","total_tax":2.8},{"rate_id":"b532df5a-dec4-11ed-8863-0ac98a3b57fb","total_tax":1.1},{"rate_id":"79a5e97e-17c0-11ee-8863-0ac98a3b57fb","total_tax":2.4}],"promotions":[],"surcharges":[],"total_tax":6.3,"total_price":40,"unit_discount":0,"unit_price":40,"unit_tax":6.3,"unit_loyalty_value":1.2,"total_cost":20,"total_discount":0,"total_loyalty_value":1.2,"unit_cost":20,"is_return":false},{"id":"c503ac82-f273-804a-11f0-02a80b22a16c","product_id":"bd18fe13-d76e-43f4-a93a-e9595f9378eb","salesperson_id":null,"tax_id":"0ac98a3b-571f-11ee-e863-17c0bf50ac3a","discount_total":20,"discount":20,"price_total":20,"price":20,"cost_total":20,"cost":20,"tax_total":3.15,"tax":3.15,"quantity":1,"loyalty_value":0.6,"note":null,"return_reason":null,"price_set":true,"status":"CONFIRMED","sequence":4,"gift_card_number":null,"tax_components":[{"rate_id":"b532b2b4-dec4-11ed-8863-0ac98a3b57fb","total_tax":1.4},{"rate_id":"b532df5a-dec4-11ed-8863-0ac98a3b57fb","total_tax":0.55},{"rate_id":"79a5e97e-17c0-11ee-8863-0ac98a3b57fb","total_tax":1.2}],"promotions":[],"surcharges":[],"total_tax":3.15,"total_price":20,"unit_discount":20,"unit_price":20,"unit_tax":3.15,"unit_loyalty_value":0.6,"total_cost":20,"total_discount":20,"total_loyalty_value":0.6,"unit_cost":20,"is_return":false},{"id":"c503ac82-f273-804a-11f0-02a81a19c196","product_id":"088d7e7c-e6cf-4913-904e-70fce0c9200e","salesperson_id":null,"tax_id":"06819b3a-2e91-11ed-f9a0-c4d5502316f5","discount_total":-0.5,"discount":-0.5,"price_total":0.5,"price":0.5,"cost_total":0,"cost":0,"tax_total":0,"tax":0,"quantity":1,"loyalty_value":0,"note":null,"return_reason":null,"price_set":true,"status":"CONFIRMED","sequence":5,"gift_card_number":null,"tax_components":[{"rate_id":"502370da-c4d5-11ed-99a0-06819b3a2e91","total_tax":0}],"promotions":[],"surcharges":[],"total_tax":0,"total_price":0.5,"unit_discount":-0.5,"unit_price":0.5,"unit_tax":0,"unit_loyalty_value":0,"total_cost":0,"total_discount":-0.5,"total_loyalty_value":0,"unit_cost":0,"is_return":false}],"payments":[{"id":"c503ac82-f273-804a-11f0-02a816318596","register_id":"06819b3a-2e91-11ed-f9a0-c4d5502c87f5","register_open_sequence_id":"0282e8ff-bc1f-11f0-f633-02771ed20267","outlet_id":"06819b3a-2e91-11ed-f9a0-c4d550292f42","retailer_payment_type_id":"caa7892a-6159-4441-80e8-6a27ea6c8960","payment_type_id":"106","name":"Loyalty","amount":4.25,"payment_date":"2025-03-16T20:48:59+00:00","deleted_at":null,"external_attributes":[],"external_applications":[],"surcharge":null,"source_id":null},{"id":"c503ac82-f273-804a-11f0-02a833a0682c","register_id":"06819b3a-2e91-11ed-f9a0-c4d5502c87f5","register_open_sequence_id":"0282e8ff-bc1f-11f0-f633-02771ed20267","outlet_id":"06819b3a-2e91-11ed-f9a0-c4d550292f42","retailer_payment_type_id":"a5237779-ff58-4cdc-bdb9-45cc65d6db45","payment_type_id":"1","name":"Cash","amount":112,"payment_date":"2025-03-16T20:49:49+00:00","deleted_at":null,"external_attributes":[],"external_applications":[],"surcharge":null,"source_id":null}],"adjustments":[],"external_applications":[],"attributes":[],"version":41931245741,"ecom_custom_charges":{"charges":[],"total":0,"total_tax":0,"total_incl":0},"total_tax":15.75,"receipt_number":"46227","total_price":100.5,"total_price_incl":116.25,"total_surcharge":0,"taxes":[{"amount":7,"id":"b532b2b4-dec4-11ed-8863-0ac98a3b57fb"},{"amount":0,"id":"502370da-c4d5-11ed-99a0-06819b3a2e91"},{"amount":2.75,"id":"b532df5a-dec4-11ed-8863-0ac98a3b57fb"},{"amount":6,"id":"79a5e97e-17c0-11ee-8863-0ac98a3b57fb"}],"_isEcomOrder":""},{"id":"bdf3ce3d-f674-974d-11ef-90b13dc9abce","outlet_id":"0ac98a3b-571f-11ee-e541-9918bad1034a","register_id":"0ac98a3b-571f-11ee-e541-9918bae98da6","user_id":"fef08829-f7bb-4f4c-bfd9-2b914c01233d","customer_id":"0200a133-d11f-11ef-e3f5-5120b2d87e30","invoice_number":"8188","source":"USER","source_id":null,"complete_open_sequence_id":null,"accounts_transaction_id":null,"has_unsynced_on_account_payments":null,"status":"CLOSED","state":"closed","note":"","short_code":"89elg5","return_for":null,"return_ids":[],"total_loyalty":0.87,"created_at":"2024-10-22T20:26:41+00:00","updated_at":"2024-10-22T20:26:41+00:00","sale_date":"2024-10-22T20:26:41+00:00","deleted_at":null,"line_items":[{"id":"bdf3ce3d-f674-974d-11ef-90b3d9967026","product_id":"c446feee-b428-47a8-a164-fac20864e5ad","salesperson_id":null,"tax_id":"0ac98a3b-571f-11ee-e541-c2109f80f7d9","discount_total":0,"discount":0,"price_total":29,"price":29,"cost_total":12,"cost":12,"tax_total":4.5675,"tax":4.5675,"quantity":1,"loyalty_value":0.87,"note":null,"return_reason":null,"price_set":false,"status":"CONFIRMED","sequence":2,"gift_card_number":null,"tax_components":[{"rate_id":"b532b2b4-dec4-11ed-8863-0ac98a3b57fb","total_tax":2.03},{"rate_id":"79a5e97e-17c0-11ee-8863-0ac98a3b57fb","total_tax":1.74},{"rate_id":"bab138fc-9918-11ee-a541-0ac98a3b57fb","total_tax":0.7975}],"promotions":[],"surcharges":[],"total_tax":4.5675,"total_price":29,"unit_discount":0,"unit_price":29,"unit_tax":4.5675,"unit_loyalty_value":0.87,"total_cost":12,"total_discount":0,"total_loyalty_value":0.87,"unit_cost":12,"is_return":false},{"id":"bdf3ce3d-f674-974d-11ef-90b3e74a9134","product_id":"dccc2736-aaaa-4c57-b6ce-d096781701d0","salesperson_id":null,"tax_id":"0ac98a3b-571f-11ee-e541-c2109f80f7d9","discount_total":3.6,"discount":3.6,"price_total":20.4,"price":20.4,"cost_total":11.5,"cost":11.5,"tax_total":3.213,"tax":3.213,"quantity":1,"loyalty_value":0,"note":null,"return_reason":null,"price_set":false,"status":"CONFIRMED","sequence":3,"gift_card_number":null,"tax_components":[{"rate_id":"b532b2b4-dec4-11ed-8863-0ac98a3b57fb","total_tax":1.428},{"rate_id":"79a5e97e-17c0-11ee-8863-0ac98a3b57fb","total_tax":1.224},{"rate_id":"bab138fc-9918-11ee-a541-0ac98a3b57fb","total_tax":0.561}],"promotions":[{"amount":-3.6,"name":"15% OFF Carts & Disposables","promotion_id":"1661037955838447616","promo_code":"","promo_code_id":"0"}],"surcharges":[],"total_tax":3.213,"total_price":20.4,"unit_discount":3.6,"unit_price":20.4,"unit_tax":3.213,"unit_loyalty_value":0,"total_cost":11.5,"total_discount":3.6,"total_loyalty_value":0,"unit_cost":11.5,"is_return":false}],"payments":[{"id":"bdf3ce3d-f674-974d-11ef-90b3f0a3f31a","register_id":"0ac98a3b-571f-11ee-e541-9918bae98da6","register_open_sequence_id":"0282e8ff-bc1f-11ef-f633-9083cc688716","outlet_id":"0ac98a3b-571f-11ee-e541-9918bad1034a","retailer_payment_type_id":"a5237779-ff58-4cdc-bdb9-45cc65d6db45","payment_type_id":"1","name":"Cash","amount":100,"payment_date":"2024-10-22T20:26:38+00:00","deleted_at":null,"external_attributes":[],"external_applications":[],"surcharge":null,"source_id":null},{"id":"bdf3ce3d-f674-974d-11ef-90b3f296c9ae","register_id":"0ac98a3b-571f-11ee-e541-9918bae98da6","register_open_sequence_id":"0282e8ff-bc1f-11ef-f633-9083cc688716","outlet_id":"0ac98a3b-571f-11ee-e541-9918bad1034a","retailer_payment_type_id":"a5237779-ff58-4cdc-bdb9-45cc65d6db45","payment_type_id":"1","name":"Cash","amount":-42.82,"payment_date":"2024-10-22T20:26:41+00:00","deleted_at":null,"external_attributes":[],"external_applications":[],"surcharge":null,"source_id":null}],"adjustments":[],"external_applications":[],"attributes":[],"version":38696849487,"ecom_custom_charges":{"charges":[],"total":0,"total_tax":0,"total_incl":0},"total_tax":7.78,"receipt_number":"8188","total_price":49.4,"total_price_incl":57.1805,"total_surcharge":0,"taxes":[{"amount":1.3585,"id":"bab138fc-9918-11ee-a541-0ac98a3b57fb"},{"amount":3.458,"id":"b532b2b4-dec4-11ed-8863-0ac98a3b57fb"},{"amount":2.964,"id":"79a5e97e-17c0-11ee-8863-0ac98a3b57fb"}],"_isEcomOrder":""},{"id":"030291d3-1e5c-82c5-11ef-8b33c1347a3a","outlet_id":"0ac98a3b-571f-11ee-e541-9918bad1034a","register_id":"0ac98a3b-571f-11ee-e541-9918bae98da6","user_id":"fef08829-f7bb-4f4c-bfd9-2b914c01233d","customer_id":"0200a133-d11f-11ef-e3f5-5120b2d87e30","invoice_number":"7824","source":"USER","source_id":null,"complete_open_sequence_id":null,"accounts_transaction_id":null,"has_unsynced_on_account_payments":null,"status":"CLOSED","state":"closed","note":"$20 off when you buy 3","short_code":"yyb1gg","return_for":null,"return_ids":[],"total_loyalty":3.38148,"created_at":"2024-10-15T20:35:55+00:00","updated_at":"2024-10-15T20:35:55+00:00","sale_date":"2024-10-15T20:35:55+00:00","deleted_at":null,"line_items":[{"id":"030291d3-1e5c-82c5-11ef-8b33c1414fda","product_id":"06819b3a-2e1f-11ed-f9a0-c4d5522bf959","salesperson_id":null,"tax_id":"06819b3a-2e91-11ed-f9a0-c4d5502316f5","discount_total":0,"discount":0,"price_total":-20,"price":20,"cost_total":0,"cost":0,"tax_total":-3.15,"tax":3.15,"quantity":-1,"loyalty_value":0,"note":null,"return_reason":null,"price_set":false,"status":"CONFIRMED","sequence":6,"gift_card_number":null,"tax_components":[{"rate_id":"b532b2b4-dec4-11ed-8863-0ac98a3b57fb","total_tax":-1.4},{"rate_id":"79a5e97e-17c0-11ee-8863-0ac98a3b57fb","total_tax":-1.2},{"rate_id":"bab138fc-9918-11ee-a541-0ac98a3b57fb","total_tax":-0.55}],"promotions":[],"surcharges":[],"total_tax":-3.15,"total_price":-20,"unit_discount":0,"unit_price":20,"unit_tax":3.15,"unit_loyalty_value":0,"total_cost":0,"total_discount":0,"total_loyalty_value":0,"unit_cost":0,"is_return":false},{"id":"030291d3-1e5c-82c5-11ef-8b34f003088a","product_id":"cb285d0b-a21f-4825-9469-bd1911831246","salesperson_id":null,"tax_id":"0ac98a3b-571f-11ee-e541-c2109f80f7d9","discount_total":0,"discount":0,"price_total":40,"price":40,"cost_total":20,"cost":20,"tax_total":6.3,"tax":6.3,"quantity":1,"loyalty_value":1.2,"note":null,"return_reason":null,"price_set":false,"status":"CONFIRMED","sequence":2,"gift_card_number":null,"tax_components":[{"rate_id":"b532b2b4-dec4-11ed-8863-0ac98a3b57fb","total_tax":2.8},{"rate_id":"79a5e97e-17c0-11ee-8863-0ac98a3b57fb","total_tax":2.4},{"rate_id":"bab138fc-9918-11ee-a541-0ac98a3b57fb","total_tax":1.1}],"promotions":[],"surcharges":[],"total_tax":6.3,"total_price":40,"unit_discount":0,"unit_price":40,"unit_tax":6.3,"unit_loyalty_value":1.2,"total_cost":20,"total_discount":0,"total_loyalty_value":1.2,"unit_cost":20,"is_return":false},{"id":"030291d3-1e5c-82c5-11ef-8b34f311a16c","product_id":"03f6046c-6dec-454c-abd1-be1d289c8779","salesperson_id":null,"tax_id":"0ac98a3b-571f-11ee-e541-c2109f80f7d9","discount_total":0,"discount":0,"price_total":40,"price":40,"cost_total":20,"cost":20,"tax_total":6.3,"tax":6.3,"quantity":1,"loyalty_value":1.2,"note":null,"return_reason":null,"price_set":false,"status":"CONFIRMED","sequence":3,"gift_card_number":null,"tax_components":[{"rate_id":"b532b2b4-dec4-11ed-8863-0ac98a3b57fb","total_tax":2.8},{"rate_id":"79a5e97e-17c0-11ee-8863-0ac98a3b57fb","total_tax":2.4},{"rate_id":"bab138fc-9918-11ee-a541-0ac98a3b57fb","total_tax":1.1}],"promotions":[],"surcharges":[],"total_tax":6.3,"total_price":40,"unit_discount":0,"unit_price":40,"unit_tax":6.3,"unit_loyalty_value":1.2,"total_cost":20,"total_discount":0,"total_loyalty_value":1.2,"unit_cost":20,"is_return":false},{"id":"030291d3-1e5c-82c5-11ef-8b34f5f2c1e0","product_id":"0589d6f9-28f2-4f05-8e2a-c7b8815ad51a","salesperson_id":null,"tax_id":"0ac98a3b-571f-11ee-e541-c2109f80f7d9","discount_total":0,"discount":0,"price_total":40,"price":40,"cost_total":20,"cost":20,"tax_total":6.3,"tax":6.3,"quantity":1,"loyalty_value":1.2,"note":null,"return_reason":null,"price_set":false,"status":"CONFIRMED","sequence":4,"gift_card_number":null,"tax_components":[{"rate_id":"b532b2b4-dec4-11ed-8863-0ac98a3b57fb","total_tax":2.8},{"rate_id":"79a5e97e-17c0-11ee-8863-0ac98a3b57fb","total_tax":2.4},{"rate_id":"bab138fc-9918-11ee-a541-0ac98a3b57fb","total_tax":1.1}],"promotions":[],"surcharges":[],"total_tax":6.3,"total_price":40,"unit_discount":0,"unit_price":40,"unit_tax":6.3,"unit_loyalty_value":1.2,"total_cost":20,"total_discount":0,"total_loyalty_value":1.2,"unit_cost":20,"is_return":false},{"id":"030291d3-1e5c-82c5-11ef-8b34f8884498","product_id":"c62c8535-f939-4606-a0e7-e810d79e41a4","salesperson_id":null,"tax_id":"0ac98a3b-571f-11ee-e541-c2109f80f7d9","discount_total":3,"discount":3,"price_total":17,"price":17,"cost_total":10,"cost":10,"tax_total":2.6775,"tax":2.6775,"quantity":1,"loyalty_value":0,"note":null,"return_reason":null,"price_set":false,"status":"CONFIRMED","sequence":5,"gift_card_number":null,"tax_components":[{"rate_id":"b532b2b4-dec4-11ed-8863-0ac98a3b57fb","total_tax":1.19},{"rate_id":"79a5e97e-17c0-11ee-8863-0ac98a3b57fb","total_tax":1.02},{"rate_id":"bab138fc-9918-11ee-a541-0ac98a3b57fb","total_tax":0.4675}],"promotions":[{"amount":-3,"name":"15% OFF Carts & Disposables","promotion_id":"1661037955838447616","promo_code":"","promo_code_id":"0"}],"surcharges":[],"total_tax":2.6775,"total_price":17,"unit_discount":3,"unit_price":17,"unit_tax":2.6775,"unit_loyalty_value":0,"total_cost":10,"total_discount":3,"total_loyalty_value":0,"unit_cost":10,"is_return":false}],"payments":[{"id":"030291d3-1e5c-82c5-11ef-8b350e4f77b0","register_id":"0ac98a3b-571f-11ee-e541-9918bae98da6","register_open_sequence_id":"0282e8ff-bc1f-11ef-f633-8b04388d58a1","outlet_id":"0ac98a3b-571f-11ee-e541-9918bad1034a","retailer_payment_type_id":"caa7892a-6159-4441-80e8-6a27ea6c8960","payment_type_id":"106","name":"Loyalty","amount":8.22,"payment_date":"2024-10-15T20:35:46+00:00","deleted_at":null,"external_attributes":[],"external_applications":[],"surcharge":null,"source_id":null},{"id":"030291d3-1e5c-82c5-11ef-8b351188f5e6","register_id":"0ac98a3b-571f-11ee-e541-9918bae98da6","register_open_sequence_id":"0282e8ff-bc1f-11ef-f633-8b04388d58a1","outlet_id":"0ac98a3b-571f-11ee-e541-9918bad1034a","retailer_payment_type_id":"a5237779-ff58-4cdc-bdb9-45cc65d6db45","payment_type_id":"1","name":"Cash","amount":150,"payment_date":"2024-10-15T20:35:51+00:00","deleted_at":null,"external_attributes":[],"external_applications":[],"surcharge":null,"source_id":null},{"id":"030291d3-1e5c-82c5-11ef-8b3513a6b674","register_id":"0ac98a3b-571f-11ee-e541-9918bae98da6","register_open_sequence_id":"0282e8ff-bc1f-11ef-f633-8b04388d58a1","outlet_id":"0ac98a3b-571f-11ee-e541-9918bad1034a","retailer_payment_type_id":"a5237779-ff58-4cdc-bdb9-45cc65d6db45","payment_type_id":"1","name":"Cash","amount":-22.79,"payment_date":"2024-10-15T20:35:55+00:00","deleted_at":null,"external_attributes":[],"external_applications":[],"surcharge":null,"source_id":null}],"adjustments":[],"external_applications":[],"attributes":[],"version":38585393192,"ecom_custom_charges":{"charges":[],"total":0,"total_tax":0,"total_incl":0},"total_tax":18.43,"receipt_number":"7824","total_price":117,"total_price_incl":135.4275,"total_surcharge":0,"taxes":[{"amount":3.2175,"id":"bab138fc-9918-11ee-a541-0ac98a3b57fb"},{"amount":8.19,"id":"b532b2b4-dec4-11ed-8863-0ac98a3b57fb"},{"amount":7.02,"id":"79a5e97e-17c0-11ee-8863-0ac98a3b57fb"}],"_isEcomOrder":false},{"id":"4b5d78ad-592f-a253-11ef-7dc891e7c138","outlet_id":"06819b3a-2e91-11ed-f9a0-c4d550292f42","register_id":"06819b3a-2e91-11ed-f9a0-c4d5502c87f5","user_id":"7ff35c1e-54a6-4441-ab36-a5775a7d7d81","customer_id":"0200a133-d11f-11ef-e3f5-5120b2d87e30","invoice_number":"32052","source":"USER","source_id":null,"complete_open_sequence_id":null,"accounts_transaction_id":null,"has_unsynced_on_account_payments":null,"status":"CLOSED","state":"closed","note":"","short_code":"l7q0im","return_for":null,"return_ids":[],"total_loyalty":4.35,"created_at":"2024-09-28T18:37:45+00:00","updated_at":"2024-09-28T18:37:45+00:00","sale_date":"2024-09-28T18:37:44+00:00","deleted_at":null,"line_items":[{"id":"4b5d78ad-592f-a253-11ef-7dc8a5f340e4","product_id":"8e85ad6e-495c-4521-be50-e87b238167b6","salesperson_id":null,"tax_id":"0ac98a3b-571f-11ed-e863-dec4b5327ac2","discount_total":0,"discount":0,"price_total":45,"price":45,"cost_total":22,"cost":22,"tax_total":4.3875,"tax":4.3875,"quantity":1,"loyalty_value":1.35,"note":null,"return_reason":null,"price_set":false,"status":"CONFIRMED","sequence":2,"gift_card_number":null,"tax_components":[{"rate_id":"b532b2b4-dec4-11ed-8863-0ac98a3b57fb","total_tax":3.15},{"rate_id":"b532df5a-dec4-11ed-8863-0ac98a3b57fb","total_tax":1.2375}],"promotions":[],"surcharges":[],"total_tax":4.3875,"total_price":45,"unit_discount":0,"unit_price":45,"unit_tax":4.3875,"unit_loyalty_value":1.35,"total_cost":22,"total_discount":0,"total_loyalty_value":1.35,"unit_cost":22,"is_return":false},{"id":"4b5d78ad-592f-a253-11ef-7dc8aa3f6da8","product_id":"385477b1-7cae-49ff-895d-de4e61f62fa5","salesperson_id":null,"tax_id":"0ac98a3b-571f-11ee-e863-17c0bf50ac3a","discount_total":0,"discount":0,"price_total":40,"price":40,"cost_total":20,"cost":20,"tax_total":6.3,"tax":6.3,"quantity":1,"loyalty_value":1.2,"note":null,"return_reason":null,"price_set":false,"status":"CONFIRMED","sequence":3,"gift_card_number":null,"tax_components":[{"rate_id":"b532b2b4-dec4-11ed-8863-0ac98a3b57fb","total_tax":2.8},{"rate_id":"b532df5a-dec4-11ed-8863-0ac98a3b57fb","total_tax":1.1},{"rate_id":"79a5e97e-17c0-11ee-8863-0ac98a3b57fb","total_tax":2.4}],"promotions":[],"surcharges":[],"total_tax":6.3,"total_price":40,"unit_discount":0,"unit_price":40,"unit_tax":6.3,"unit_loyalty_value":1.2,"total_cost":20,"total_discount":0,"total_loyalty_value":1.2,"unit_cost":20,"is_return":false},{"id":"4b5d78ad-592f-a253-11ef-7dc8acbc8a7a","product_id":"cb285d0b-a21f-4825-9469-bd1911831246","salesperson_id":null,"tax_id":"0ac98a3b-571f-11ee-e863-17c0bf50ac3a","discount_total":0,"discount":0,"price_total":40,"price":40,"cost_total":20,"cost":20,"tax_total":6.3,"tax":6.3,"quantity":1,"loyalty_value":1.2,"note":null,"return_reason":null,"price_set":false,"status":"CONFIRMED","sequence":4,"gift_card_number":null,"tax_components":[{"rate_id":"b532b2b4-dec4-11ed-8863-0ac98a3b57fb","total_tax":2.8},{"rate_id":"b532df5a-dec4-11ed-8863-0ac98a3b57fb","total_tax":1.1},{"rate_id":"79a5e97e-17c0-11ee-8863-0ac98a3b57fb","total_tax":2.4}],"promotions":[],"surcharges":[],"total_tax":6.3,"total_price":40,"unit_discount":0,"unit_price":40,"unit_tax":6.3,"unit_loyalty_value":1.2,"total_cost":20,"total_discount":0,"total_loyalty_value":1.2,"unit_cost":20,"is_return":false},{"id":"4b5d78ad-592f-a253-11ef-7dc8af68d9cc","product_id":"effe6538-7f77-4fed-852f-931c7a5fb615","salesperson_id":null,"tax_id":"0ac98a3b-571f-11ee-e863-17c0bf50ac3a","discount_total":20,"discount":20,"price_total":20,"price":20,"cost_total":20,"cost":20,"tax_total":3.15,"tax":3.15,"quantity":1,"loyalty_value":0.6,"note":null,"return_reason":null,"price_set":true,"status":"CONFIRMED","sequence":5,"gift_card_number":null,"tax_components":[{"rate_id":"b532b2b4-dec4-11ed-8863-0ac98a3b57fb","total_tax":1.4},{"rate_id":"b532df5a-dec4-11ed-8863-0ac98a3b57fb","total_tax":0.55},{"rate_id":"79a5e97e-17c0-11ee-8863-0ac98a3b57fb","total_tax":1.2}],"promotions":[],"surcharges":[],"total_tax":3.15,"total_price":20,"unit_discount":20,"unit_price":20,"unit_tax":3.15,"unit_loyalty_value":0.6,"total_cost":20,"total_discount":20,"total_loyalty_value":0.6,"unit_cost":20,"is_return":false}],"payments":[{"id":"4b5d78ad-592f-a253-11ef-7dc8be93e2ca","register_id":"06819b3a-2e91-11ed-f9a0-c4d5502c87f5","register_open_sequence_id":"0282e8ff-bc1f-11ef-f633-7da9f86f0706","outlet_id":"06819b3a-2e91-11ed-f9a0-c4d550292f42","retailer_payment_type_id":"a5237779-ff58-4cdc-bdb9-45cc65d6db45","payment_type_id":"1","name":"Cash","amount":200,"payment_date":"2024-09-28T18:37:41+00:00","deleted_at":null,"external_attributes":[],"external_applications":[],"surcharge":null,"source_id":null},{"id":"4b5d78ad-592f-a253-11ef-7dc8c094265c","register_id":"06819b3a-2e91-11ed-f9a0-c4d5502c87f5","register_open_sequence_id":"0282e8ff-bc1f-11ef-f633-7da9f86f0706","outlet_id":"06819b3a-2e91-11ed-f9a0-c4d550292f42","retailer_payment_type_id":"a5237779-ff58-4cdc-bdb9-45cc65d6db45","payment_type_id":"1","name":"Cash","amount":-34.86,"payment_date":"2024-09-28T18:37:44+00:00","deleted_at":null,"external_attributes":[],"external_applications":[],"surcharge":null,"source_id":null}],"adjustments":[],"external_applications":[],"attributes":[],"version":38322493466,"ecom_custom_charges":{"charges":[],"total":0,"total_tax":0,"total_incl":0},"total_tax":20.14,"receipt_number":"32052","total_price":145,"total_price_incl":165.1375,"total_surcharge":0,"taxes":[{"amount":10.15,"id":"b532b2b4-dec4-11ed-8863-0ac98a3b57fb"},{"amount":3.9875,"id":"b532df5a-dec4-11ed-8863-0ac98a3b57fb"},{"amount":6,"id":"79a5e97e-17c0-11ee-8863-0ac98a3b57fb"}],"_isEcomOrder":""},{"id":"a9224cf8-00c3-9fc4-11ef-511fb02af244","outlet_id":"06819b3a-2e91-11ed-f9a0-c4d550292f42","register_id":"06819b3a-2e91-11ed-f9a0-c4d5502c87f5","user_id":"3c2d6f1d-c7ac-4f14-ba6e-664ab51f8000","customer_id":"0200a133-d11f-11ef-e3f5-5120b2d87e30","invoice_number":"26915","source":"USER","source_id":null,"complete_open_sequence_id":null,"accounts_transaction_id":null,"has_unsynced_on_account_payments":null,"status":"CLOSED","state":"closed","note":"3 for $100","short_code":"3rg5q9","return_for":null,"return_ids":[],"total_loyalty":3.87,"created_at":"2024-08-02T22:44:11+00:00","updated_at":"2024-08-02T22:44:11+00:00","sale_date":"2024-08-02T22:44:10+00:00","deleted_at":null,"line_items":[{"id":"a9224cf8-00c3-9fc4-11ef-511fb037bfec","product_id":"06819b3a-2e1f-11ed-f9a0-c4d5522bf959","salesperson_id":null,"tax_id":"06819b3a-2e91-11ed-f9a0-c4d5502316f5","discount_total":0,"discount":0,"price_total":-20,"price":20,"cost_total":0,"cost":0,"tax_total":-3.06628,"tax":3.06628,"quantity":-1,"loyalty_value":0,"note":null,"return_reason":null,"price_set":false,"status":"CONFIRMED","sequence":6,"gift_card_number":null,"tax_components":[{"rate_id":"b532b2b4-dec4-11ed-8863-0ac98a3b57fb","total_tax":-1.4},{"rate_id":"b532df5a-dec4-11ed-8863-0ac98a3b57fb","total_tax":-0.55},{"rate_id":"79a5e97e-17c0-11ee-8863-0ac98a3b57fb","total_tax":-1.11628}],"promotions":[],"surcharges":[],"total_tax":-3.06628,"total_price":-20,"unit_discount":0,"unit_price":20,"unit_tax":3.06628,"unit_loyalty_value":0,"total_cost":0,"total_discount":0,"total_loyalty_value":0,"unit_cost":0,"is_return":false},{"id":"a9224cf8-00c3-9fc4-11ef-512084840cce","product_id":"7af68e89-75bd-4372-84e4-93baeaa5d129","salesperson_id":null,"tax_id":"0ac98a3b-571f-11ee-e863-17c0bf50ac3a","discount_total":0,"discount":0,"price_total":40,"price":40,"cost_total":20,"cost":20,"tax_total":6.3,"tax":6.3,"quantity":1,"loyalty_value":1.2,"note":null,"return_reason":null,"price_set":false,"status":"CONFIRMED","sequence":2,"gift_card_number":null,"tax_components":[{"rate_id":"b532b2b4-dec4-11ed-8863-0ac98a3b57fb","total_tax":2.8},{"rate_id":"b532df5a-dec4-11ed-8863-0ac98a3b57fb","total_tax":1.1},{"rate_id":"79a5e97e-17c0-11ee-8863-0ac98a3b57fb","total_tax":2.4}],"promotions":[],"surcharges":[],"total_tax":6.3,"total_price":40,"unit_discount":0,"unit_price":40,"unit_tax":6.3,"unit_loyalty_value":1.2,"total_cost":20,"total_discount":0,"total_loyalty_value":1.2,"unit_cost":20,"is_return":false},{"id":"a9224cf8-00c3-9fc4-11ef-51208936638e","product_id":"03f6046c-6dec-454c-abd1-be1d289c8779","salesperson_id":null,"tax_id":"0ac98a3b-571f-11ee-e863-17c0bf50ac3a","discount_total":0,"discount":0,"price_total":40,"price":40,"cost_total":20,"cost":20,"tax_total":6.3,"tax":6.3,"quantity":1,"loyalty_value":1.2,"note":null,"return_reason":null,"price_set":false,"status":"CONFIRMED","sequence":3,"gift_card_number":null,"tax_components":[{"rate_id":"b532b2b4-dec4-11ed-8863-0ac98a3b57fb","total_tax":2.8},{"rate_id":"b532df5a-dec4-11ed-8863-0ac98a3b57fb","total_tax":1.1},{"rate_id":"79a5e97e-17c0-11ee-8863-0ac98a3b57fb","total_tax":2.4}],"promotions":[],"surcharges":[],"total_tax":6.3,"total_price":40,"unit_discount":0,"unit_price":40,"unit_tax":6.3,"unit_loyalty_value":1.2,"total_cost":20,"total_discount":0,"total_loyalty_value":1.2,"unit_cost":20,"is_return":false},{"id":"a9224cf8-00c3-9fc4-11ef-51208f00239a","product_id":"effe6538-7f77-4fed-852f-931c7a5fb615","salesperson_id":null,"tax_id":"0ac98a3b-571f-11ee-e863-17c0bf50ac3a","discount_total":0,"discount":0,"price_total":40,"price":40,"cost_total":20,"cost":20,"tax_total":6.3,"tax":6.3,"quantity":1,"loyalty_value":1.2,"note":null,"return_reason":null,"price_set":false,"status":"CONFIRMED","sequence":4,"gift_card_number":null,"tax_components":[{"rate_id":"b532b2b4-dec4-11ed-8863-0ac98a3b57fb","total_tax":2.8},{"rate_id":"b532df5a-dec4-11ed-8863-0ac98a3b57fb","total_tax":1.1},{"rate_id":"79a5e97e-17c0-11ee-8863-0ac98a3b57fb","total_tax":2.4}],"promotions":[],"surcharges":[],"total_tax":6.3,"total_price":40,"unit_discount":0,"unit_price":40,"unit_tax":6.3,"unit_loyalty_value":1.2,"total_cost":20,"total_discount":0,"total_loyalty_value":1.2,"unit_cost":20,"is_return":false},{"id":"a9224cf8-00c3-9fc4-11ef-51209f615d3a","product_id":"e002e906-f47f-4acc-9e02-e4785919cc9a","salesperson_id":null,"tax_id":"0ac98a3b-571f-11ed-e863-dec4b5327ac2","discount_total":0,"discount":0,"price_total":9,"price":9,"cost_total":4.38,"cost":4.38,"tax_total":0.8775,"tax":0.8775,"quantity":1,"loyalty_value":0.27,"note":null,"return_reason":null,"price_set":false,"status":"CONFIRMED","sequence":5,"gift_card_number":null,"tax_components":[{"rate_id":"b532b2b4-dec4-11ed-8863-0ac98a3b57fb","total_tax":0.63},{"rate_id":"b532df5a-dec4-11ed-8863-0ac98a3b57fb","total_tax":0.2475}],"promotions":[],"surcharges":[],"total_tax":0.8775,"total_price":9,"unit_discount":0,"unit_price":9,"unit_tax":0.8775,"unit_loyalty_value":0.27,"total_cost":4.38,"total_discount":0,"total_loyalty_value":0.27,"unit_cost":4.38,"is_return":false}],"payments":[{"id":"a9224cf8-00c3-9fc4-11ef-5120b8f1c62c","register_id":"06819b3a-2e91-11ed-f9a0-c4d5502c87f5","register_open_sequence_id":"0200a133-d11f-11ef-e3f5-50df4b1d9583","outlet_id":"06819b3a-2e91-11ed-f9a0-c4d550292f42","retailer_payment_type_id":"a5237779-ff58-4cdc-bdb9-45cc65d6db45","payment_type_id":"1","name":"Cash","amount":140,"payment_date":"2024-08-02T22:44:05+00:00","deleted_at":null,"external_attributes":[],"external_applications":[],"surcharge":null,"source_id":null},{"id":"a9224cf8-00c3-9fc4-11ef-5120bbcaa88c","register_id":"06819b3a-2e91-11ed-f9a0-c4d5502c87f5","register_open_sequence_id":"0200a133-d11f-11ef-e3f5-50df4b1d9583","outlet_id":"06819b3a-2e91-11ed-f9a0-c4d550292f42","retailer_payment_type_id":"a5237779-ff58-4cdc-bdb9-45cc65d6db45","payment_type_id":"1","name":"Cash","amount":-14.29,"payment_date":"2024-08-02T22:44:10+00:00","deleted_at":null,"external_attributes":[],"external_applications":[],"surcharge":null,"source_id":null}],"adjustments":[],"external_applications":[],"attributes":[],"version":37420010835,"ecom_custom_charges":{"charges":[],"total":0,"total_tax":0,"total_incl":0},"total_tax":16.71,"receipt_number":"26915","total_price":109,"total_price_incl":125.71122,"total_surcharge":0,"taxes":[{"amount":7.63,"id":"b532b2b4-dec4-11ed-8863-0ac98a3b57fb"},{"amount":2.9975,"id":"b532df5a-dec4-11ed-8863-0ac98a3b57fb"},{"amount":6.08372,"id":"79a5e97e-17c0-11ee-8863-0ac98a3b57fb"}],"_isEcomOrder":false}],"cachedAt":"2026-01-15T17:15:17.216Z"}